projects/zaram_training_course/02_combinational_logic/06_barrel_shifter/barrel_shifter.v
module barrel_shifter
#(
	parameter bit_size = 4
)
(
	input [bit_size-1:0] data,
	input [$clog2(bit_size)-1:0] num_shift, 	// number to shift
	input direction, 		// 0: left, 1:right
	input [1:0] sel,		// 0: logical shift, 1:arithmetic shift, 2:rotate
	output reg [bit_size-1:0] out,
	output reg overflow			//logical and arithmetic overflow
);
	
	always @ (*) begin
		case(sel)
			0 : {overflow, out} = direction ? (data >> num_shift) : (data << num_shift);
			1 : {overflow, out} = direction ? (data >>> num_shift) : (data <<< num_shift);
			2 : out = direction ? ((data >> num_shift) | (data << (bit_size-num_shift))) :  ((data << num_shift) | (data >> (bit_size-num_shift))); 
			default : out = 0;
			endcase
		end
	
	`ifdef	DEBUG
		reg [8*32-1:0] directMonitor;
		reg [8*32-1:0] selMonitor;
		always @ (*) begin
			case(direction)
				0 : directMonitor = "left";
				1 : directMonitor = "right";
			endcase
			case(sel)
				0 : selMonitor = "logical shift";
				1 : selMonitor = "arith shift";
				2 : selMonitor = "rotate";
			endcase
		end
	`endif

endmodule

projects/zaram_training_course/02_combinational_logic/06_barrel_shifter/barrel_shifter_tb.v

// --------------------------------------------------
//	Define Global Variables
// --------------------------------------------------
`define	CLKFREQ		100		// Clock Freq. (Unit: MHz)
`define	SIMCYCLE	`NVEC	// Sim. Cycles
`define NVEC		50		// # of Test Vector
`define DEBUG

// --------------------------------------------------
//	Includes
// --------------------------------------------------
`include "barrel_shifter.v"

module barrel_shifter_tb();
	parameter bit_size = 16;
	reg [bit_size-1:0] data;
	reg [$clog2(bit_size)-1:0] num_shift; 	// number to shift
	reg direction; 		// 0: left, 1:right
	reg [1:0] sel;		// 0: logical shift, 1:arithmetic shift, 2:rotate
	wire	 [bit_size-1:0] out;
	wire	 overflow;			//logical and arithmetic overflow;

	barrel_shifter
	#(
		.bit_size			(bit_size			)
	)
	u_barrel_shifter(
		.data				(data				),
		.num_shift			(num_shift			),
		.direction			(direction			),
		.sel				(sel				),
		.out				(out				),
		.overflow			(overflow			)
	);


// --------------------------------------------------
//	Tasks
// --------------------------------------------------
	reg [8*32-1:0] taskState;
	integer err = 0;

	task init;
		begin
//			taskState = "Init";
			data	= 0;
			num_shift = 0;
			direction = 0;
			sel =0;

		end
	endtask
/*
	task resetReleaseAfterNCycles;
		input [9:0] n;
		begin
			taskState = "Reset On";
			rstn = 1'b0;
			#(1000/`CLKFREQ);
			rstn = 1'b1; 
			taskState = "Reset OFF";
		end
	endtask
*/

// --------------------------------------------------
//	Test Stimulus
// --------------------------------------------------
	integer		i, j;
	initial begin
		init();
//		resetReleaseAfterNCycles(4);

		for (i=0; i<`SIMCYCLE; i++) begin
			data = $urandom;
			num_shift = $urandom;
			direction = $urandom;
			sel = $urandom;
		#(1000/`CLKFREQ);
		end
		$finish;
	end

// --------------------------------------------------
//	Dump VCD
// --------------------------------------------------

	reg [8*32-1:0]  vcd_file;
    initial begin
        if ($value$plusargs("vcd_file=%s", vcd_file)) begin
            $dumpfile(vcd_file);
            $dumpvars;
        end
    end
endmodule

projects/zaram_training_course/02_combinational_logic/06_barrel_shifter/vcd/barrel_shifter.vcd
$date
	Fri Jun 28 15:25:40 2024
$end
$version
	Icarus Verilog
$end
$timescale
	1ps
$end
$scope module barrel_shifter_tb $end
$var wire 1 ! overflow $end
$var wire 8 " out [7:0] $end
$var reg 8 # data [7:0] $end
$var reg 1 $ direction $end
$var reg 3 % num_shift [2:0] $end
$var reg 2 & sel [1:0] $end
$var reg 256 ' vcd_file [255:0] $end
$var integer 32 ( err [31:0] $end
$var integer 32 ) i [31:0] $end
$scope module u_barrel_shifter $end
$var wire 8 * data [7:0] $end
$var wire 1 $ direction $end
$var wire 3 + num_shift [2:0] $end
$var wire 2 , sel [1:0] $end
$var reg 256 - directMonitor [255:0] $end
$var reg 8 . out [7:0] $end
$var reg 1 ! overflow $end
$var reg 256 / selMonitor [255:0] $end
$upscope $end
$scope task init $end
$upscope $end
$upscope $end
$enddefinitions $end
#0
$dumpvars
bx /
b0 .
b111001001101001011001110110100001110100 -
b11 ,
b1 +
b100100 *
b0 )
b0 (
b1011100010111101110110011000110110010000101111011000100110000101110010011100100110010101101100010111110111001101101000011010010110011001110100011001010111001000101110011101100110001101100100 '
b11 &
b1 %
1$
b100100 #
b0 "
x!
$end
#10000
b11100100110111101110100011000010111010001100101 /
b1101000 "
b1101000 .
b10 &
b10 ,
b101 %
b101 +
b1101 #
b1101 *
b1 )
#20000
b110000101110010011010010111010001101000001000000111001101101000011010010110011001110100 /
b1101100011001010110011001110100 -
0!
b100000 "
b100000 .
b1 &
b1 ,
0$
b1 #
b1 *
b10 )
#30000
b11100100110111101110100011000010111010001100101 /
b111001001101001011001110110100001110100 -
b11011110 "
b11011110 .
b10 &
b10 ,
1$
b100 %
b100 +
b11101101 #
b11101101 *
b11 )
#40000
b0 "
b0 .
b11 &
b11 ,
b10 %
b10 +
b11000101 #
b11000101 *
b100 )
#50000
b1101100011001010110011001110100 -
b1001 "
b1001 .
b10 &
b10 ,
0$
b111 %
b111 +
b10010 #
b10010 *
b101 )
#60000
b110000101110010011010010111010001101000001000000111001101101000011010010110011001110100 /
1!
b0 "
b0 .
b1 &
b1 ,
b101 %
b101 +
b11101000 #
b11101000 *
b110 )
#70000
b11100100110111101110100011000010111010001100101 /
b111001001101001011001110110100001110100 -
b1101001 "
b1101001 .
b10 &
b10 ,
1$
b101101 #
b101101 *
b111 )
#80000
b110000101110010011010010111010001101000001000000111001101101000011010010110011001110100 /
b1101100011001010110011001110100 -
0!
b10000000 "
b10000000 .
b1 &
b1 ,
0$
b0 %
b0 +
b10000000 #
b10000000 *
b1000 )
#90000
b111001001101001011001110110100001110100 -
b0 "
b0 .
b11 &
b11 ,
1$
b11 %
b11 +
b10010110 #
b10010110 *
b1001 )
#100000
b11100100110111101110100011000010111010001100101 /
b1101100011001010110011001110100 -
b1101101 "
b1101101 .
b10 &
b10 ,
0$
b101 %
b101 +
b1101011 #
b1101011 *
b1010 )
#110000
b111001001101001011001110110100001110100 -
b111010 "
b111010 .
1$
b111 %
b111 +
b11101 #
b11101 *
b1011 )
#120000
b1101100011001010110011001110100 -
b10101100 "
b10101100 .
0$
b100 %
b100 +
b11001010 #
b11001010 *
b1100 )
#130000
b110000101110010011010010111010001101000001000000111001101101000011010010110011001110100 /
b1000001 "
b1000001 .
b1 &
b1 ,
b0 %
b0 +
b1000001 #
b1000001 *
b1101 )
#140000
b11100100110111101110100011000010111010001100101 /
b11111010 "
b11111010 .
b10 &
b10 ,
b110 %
b110 +
b11101011 #
b11101011 *
b1110 )
#150000
b110000101110010011010010111010001101000001000000111001101101000011010010110011001110100 /
b111001001101001011001110110100001110100 -
b101111 "
b101111 .
b1 &
b1 ,
1$
b10 %
b10 +
b10111100 #
b10111100 *
b1111 )
#160000
b11100100110111101110100011000010111010001100101 /
b1011 "
b1011 .
b10 &
b10 ,
b111 %
b111 +
b10000101 #
b10000101 *
b10000 )
#170000
b110000101110010011010010111010001101000001000000111001101101000011010010110011001110100 /
b11 "
b11 .
b1 &
b1 ,
b101 %
b101 +
b1111110 #
b1111110 *
b10001 )
#180000
b0 "
b0 .
b11 &
b11 ,
b100 %
b100 +
b1100010 #
b1100010 *
b10010 )
#190000
b1101100011011110110011101101001011000110110000101101100001000000111001101101000011010010110011001110100 /
b1 "
b1 .
b0 &
b0 ,
b111 %
b111 +
b11111000 #
b11111000 *
b10011 )
#200000
b101101 "
b101101 .
b1 %
b1 +
b1011011 #
b1011011 *
b10100 )
#210000
b1101100011001010110011001110100 -
1!
b10101110 "
b10101110 .
0$
b11010111 #
b11010111 *
b10101 )
#220000
b110000101110010011010010111010001101000001000000111001101101000011010010110011001110100 /
b111001001101001011001110110100001110100 -
0!
b11000010 "
b11000010 .
b1 &
b1 ,
1$
b0 %
b0 +
b11000010 #
b11000010 *
b10110 )
#230000
b0 "
b0 .
b110 %
b110 +
b10010 #
b10010 *
b10111 )
#240000
b1101100011011110110011101101001011000110110000101101100001000000111001101101000011010010110011001110100 /
b11 "
b11 .
b0 &
b0 ,
b11 %
b11 +
b11111 #
b11111 *
b11000 )
#250000
b11100100110111101110100011000010111010001100101 /
b10101101 "
b10101101 .
b10 &
b10 ,
b1 %
b1 +
b1011011 #
b1011011 *
b11001 )
#260000
b1101100011011110110011101101001011000110110000101101100001000000111001101101000011010010110011001110100 /
b1101100011001010110011001110100 -
b0 "
b0 .
b0 &
b0 ,
0$
b110 %
b110 +
b1011000 #
b1011000 *
b11010 )
#270000
b111001001101001011001110110100001110100 -
b11 &
b11 ,
1$
b11111010 #
b11111010 *
b11011 )
#280000
b101 "
b101 .
b0 &
b0 ,
b11 %
b11 +
b101111 #
b101111 *
b11100 )
#290000
b11100100110111101110100011000010111010001100101 /
b1101100011001010110011001110100 -
b10111111 "
b10111111 .
b10 &
b10 ,
0$
b11110111 #
b11110111 *
b11101 )
#300000
b110000101110010011010010111010001101000001000000111001101101000011010010110011001110100 /
1!
b100000 "
b100000 .
b1 &
b1 ,
b101 %
b101 +
b101001 #
b101001 *
b11110 )
#310000
b1101100011011110110011101101001011000110110000101101100001000000111001101101000011010010110011001110100 /
b111001001101001011001110110100001110100 -
0!
b1 "
b1 .
b0 &
b0 ,
1$
b111 %
b111 +
b10110101 #
b10110101 *
b11111 )
#320000
b11100100110111101110100011000010111010001100101 /
b110100 "
b110100 .
b10 &
b10 ,
b10 %
b10 +
b11010000 #
b11010000 *
b100000 )
#330000
b0 "
b0 .
b11 &
b11 ,
b11011100 #
b11011100 *
b100001 )
#340000
b1011001 "
b1011001 .
b10 &
b10 ,
b110 %
b110 +
b1010110 #
b1010110 *
b100010 )
#350000
b1101100011011110110011101101001011000110110000101101100001000000111001101101000011010010110011001110100 /
b10110110 "
b10110110 .
b0 &
b0 ,
b0 %
b0 +
b10110110 #
b10110110 *
b100011 )
#360000
b110000101110010011010010111010001101000001000000111001101101000011010010110011001110100 /
b1101100011001010110011001110100 -
b10100000 "
b10100000 .
b1 &
b1 ,
0$
b11 %
b11 +
b10010100 #
b10010100 *
b100100 )
#370000
b111001001101001011001110110100001110100 -
b110 "
b110 .
1$
b101 %
b101 +
b11011011 #
b11011011 *
b100101 )
#380000
b1101100011001010110011001110100 -
1!
b11011000 "
b11011000 .
0$
b10 %
b10 +
b1110110 #
b1110110 *
b100110 )
#390000
b111001001101001011001110110100001110100 -
0!
b100 "
b100 .
1$
b100 %
b100 +
b1000110 #
b1000110 *
b100111 )
#400000
b1101100011001010110011001110100 -
b10110100 "
b10110100 .
0$
b0 %
b0 +
b10110100 #
b10110100 *
b101000 )
#410000
b1101100011011110110011101101001011000110110000101101100001000000111001101101000011010010110011001110100 /
1!
b11000000 "
b11000000 .
b0 &
b0 ,
b110 %
b110 +
b11000111 #
b11000111 *
b101001 )
#420000
b11100100110111101110100011000010111010001100101 /
b11111011 "
b11111011 .
b10 &
b10 ,
b1 %
b1 +
b11111101 #
b11111101 *
b101010 )
#430000
b1101100011011110110011101101001011000110110000101101100001000000111001101101000011010010110011001110100 /
b1000000 "
b1000000 .
b0 &
b0 ,
b101 %
b101 +
b11011010 #
b11011010 *
b101011 )
#440000
b11100100110111101110100011000010111010001100101 /
b11001101 "
b11001101 .
b10 &
b10 ,
b10 %
b10 +
b1110011 #
b1110011 *
b101100 )
#450000
b111001001101001011001110110100001110100 -
b0 "
b0 .
b11 &
b11 ,
1$
b11010101 #
b11010101 *
b101101 )
#460000
b1101100011001010110011001110100 -
b10010110 "
b10010110 .
b10 &
b10 ,
0$
b0 %
b0 +
b10010110 #
b10010110 *
b101110 )
#470000
b1101100011011110110011101101001011000110110000101101100001000000111001101101000011010010110011001110100 /
b11010000 "
b11010000 .
b0 &
b0 ,
b100 %
b100 +
b1111101 #
b1111101 *
b101111 )
#480000
b110000101110010011010010111010001101000001000000111001101101000011010010110011001110100 /
b111001001101001011001110110100001110100 -
0!
b1111 "
b1111 .
b1 &
b1 ,
1$
b11 %
b11 +
b1111110 #
b1111110 *
b110000 )
#490000
b1111101 "
b1111101 .
b1 %
b1 +
b11111010 #
b11111010 *
b110001 )
#500000
b110010 )
