projects/zaram_training_course/02_combinational_logic/06_barrel_shifter/barrel_shifter.v
module barrel_shifter
#(
	parameter bit_size = 4
)
(
	input [bit_size-1:0] data,
	input [$clog2(bit_size)-1:0] num_shift, 	// number to shift
	input direction, 		// 0: left, 1:right
	input [1:0] sel,		// 0: logical shift, 1:arithmetic shift, 2:rotate
	output reg [bit_size-1:0] out,
	output reg overflow			//logical and arithmetic overflow
);
	
	always @ (*) begin
		case(sel)
			0 : {overflow, out} = direction ? (data >> num_shift) : (data << num_shift);
			1 : {overflow, out} = direction ? (data >>> num_shift) : (data <<< num_shift);
			2 : out = direction ? ((data >> num_shift) | (data << (bit_size-num_shift))) :  ((data << num_shift) | (data >> (bit_size-num_shift))); 
			default : out = 0;
			endcase
		end
	
	`ifdef	DEBUG
		reg [8*32-1:0] directMonitor;
		reg [8*32-1:0] selMonitor;
		always @ (*) begin
			case(direction)
				0 : directMonitor = "left";
				1 : directMonitor = "right";
			endcase
			case(sel)
				0 : selMonitor = "logical shift";
				1 : selMonitor = "arith shift";
				2 : selMonitor = "rotate";
			endcase
		end
	`endif

endmodule

projects/zaram_training_course/02_combinational_logic/06_barrel_shifter/barrel_shifter_tb.v

// --------------------------------------------------
//	Define Global Variables
// --------------------------------------------------
`define	CLKFREQ		100		// Clock Freq. (Unit: MHz)
`define	SIMCYCLE	`NVEC	// Sim. Cycles
`define NVEC		50		// # of Test Vector
`define DEBUG

// --------------------------------------------------
//	Includes
// --------------------------------------------------
`include "barrel_shifter.v"

module barrel_shifter_tb();
	parameter bit_size = 16;
	reg [bit_size-1:0] data;
	reg [$clog2(bit_size)-1:0] num_shift; 	// number to shift
	reg direction; 		// 0: left, 1:right
	reg [1:0] sel;		// 0: logical shift, 1:arithmetic shift, 2:rotate
	wire	 [bit_size-1:0] out;
	wire	 overflow;			//logical and arithmetic overflow;

	barrel_shifter
	#(
		.bit_size			(bit_size			)
	)
	u_barrel_shifter(
		.data				(data				),
		.num_shift			(num_shift			),
		.direction			(direction			),
		.sel				(sel				),
		.out				(out				),
		.overflow			(overflow			)
	);


// --------------------------------------------------
//	Tasks
// --------------------------------------------------
	reg [8*32-1:0] taskState;
	integer err = 0;

	task init;
		begin
//			taskState = "Init";
			data	= 0;
			num_shift = 0;
			direction = 0;
			sel =0;

		end
	endtask
/*
	task resetReleaseAfterNCycles;
		input [9:0] n;
		begin
			taskState = "Reset On";
			rstn = 1'b0;
			#(1000/`CLKFREQ);
			rstn = 1'b1; 
			taskState = "Reset OFF";
		end
	endtask
*/

// --------------------------------------------------
//	Test Stimulus
// --------------------------------------------------
	integer		i, j;
	initial begin
		init();
//		resetReleaseAfterNCycles(4);

		for (i=0; i<`SIMCYCLE; i++) begin
			data = $urandom;
			num_shift = $urandom;
			direction = $urandom;
			sel = $urandom;
		#(1000/`CLKFREQ);
		end
		$finish;
	end

// --------------------------------------------------
//	Dump VCD
// --------------------------------------------------

	reg [8*32-1:0]  vcd_file;
    initial begin
        if ($value$plusargs("vcd_file=%s", vcd_file)) begin
            $dumpfile(vcd_file);
            $dumpvars;
        end
    end
endmodule

projects/zaram_training_course/02_combinational_logic/06_barrel_shifter/vcd/barrel_shifter.vcd
$date
	Wed Jun 26 10:29:11 2024
$end
$version
	Icarus Verilog
$end
$timescale
	1ps
$end
$scope module barrel_shifter_tb $end
$var wire 1 ! overflow $end
$var wire 16 " out [15:0] $end
$var reg 16 # data [15:0] $end
$var reg 1 $ direction $end
$var reg 4 % num_shift [3:0] $end
$var reg 2 & sel [1:0] $end
$var reg 256 ' vcd_file [255:0] $end
$var integer 32 ( err [31:0] $end
$var integer 32 ) i [31:0] $end
$scope module u_barrel_shifter $end
$var wire 16 * data [15:0] $end
$var wire 1 $ direction $end
$var wire 4 + num_shift [3:0] $end
$var wire 2 , sel [1:0] $end
$var reg 256 - directMonitor [255:0] $end
$var reg 16 . out [15:0] $end
$var reg 1 ! overflow $end
$var reg 256 / selMonitor [255:0] $end
$upscope $end
$scope task init $end
$upscope $end
$upscope $end
$enddefinitions $end
#0
$dumpvars
bx /
b0 .
b111001001101001011001110110100001110100 -
b11 ,
b1 +
b11010100100100 *
b0 )
b0 (
b1011100010111101110110011000110110010000101111011000100110000101110010011100100110010101101100010111110111001101101000011010010110011001110100011001010111001000101110011101100110001101100100 '
b11 &
b1 %
1$
b11010100100100 #
b0 "
x!
$end
#10000
b11100100110111101110100011000010111010001100101 /
b1101100001101011 "
b1101100001101011 .
b10 &
b10 ,
b1101 %
b1101 +
b111101100001101 #
b111101100001101 *
b1 )
#20000
b110000101110010011010010111010001101000001000000111001101101000011010010110011001110100 /
b1101100011001010110011001110100 -
0!
b10000000000000 "
b10000000000000 .
b1 &
b1 ,
0$
b1110001100000001 #
b1110001100000001 *
b10 )
#30000
b11100100110111101110100011000010111010001100101 /
b111001001101001011001110110100001110100 -
b111111011010101 "
b111111011010101 .
b10 &
b10 ,
1$
b1100 %
b1100 +
b101011111101101 #
b101011111101101 *
b11 )
#40000
b0 "
b0 .
b11 &
b11 ,
b1010 %
b1010 +
b1000010011000101 #
b1000010011000101 *
b100 )
#50000
b1101100011001010110011001110100 -
b110101100001001 "
b110101100001001 .
b10 &
b10 ,
0$
b1111 %
b1111 +
b1101011000010010 #
b1101011000010010 *
b101 )
#60000
b110000101110010011010010111010001101000001000000111001101101000011010010110011001110100 /
1!
b101110100000000 "
b101110100000000 .
b1 &
b1 ,
b101 %
b101 +
b111101011101000 #
b111101011101000 *
b110 )
#70000
b11100100110111101110100011000010111010001100101 /
b111001001101001011001110110100001110100 -
b110101011000001 "
b110101011000001 .
b10 &
b10 ,
1$
b101100000101101 #
b101100000101101 *
b111 )
#80000
b110000101110010011010010111010001101000001000000111001101101000011010010110011001110100 /
b1101100011001010110011001110100 -
0!
b10001010000000 "
b10001010000000 .
b1 &
b1 ,
0$
b0 %
b0 +
b10001010000000 #
b10001010000000 *
b1000 )
#90000
b111001001101001011001110110100001110100 -
b0 "
b0 .
b11 &
b11 ,
1$
b11 %
b11 +
b11111010010110 #
b11111010010110 *
b1001 )
#100000
b11100100110111101110100011000010111010001100101 /
b1101100011001010110011001110100 -
b1010110101111011 "
b1010110101111011 .
b10 &
b10 ,
0$
b101 %
b101 +
b1101110101101011 #
b1101110101101011 *
b1010 )
#110000
b111001001101001011001110110100001110100 -
b1101001000111011 "
b1101001000111011 .
1$
b1111 %
b1111 +
b1110100100011101 #
b1110100100011101 *
b1011 )
#120000
b1101100011001010110011001110100 -
b1010000010101100 "
b1010000010101100 .
0$
b1100 %
b1100 +
b101011001010 #
b101011001010 *
b1100 )
#130000
b110000101110010011010010111010001101000001000000111001101101000011010010110011001110100 /
1!
b100000100000000 "
b100000100000000 .
b1 &
b1 ,
b1000 %
b1000 +
b1011001101000001 #
b1011001101000001 *
b1101 )
#140000
b11100100110111101110100011000010111010001100101 /
b111101011000011 "
b111101011000011 .
b10 &
b10 ,
b110 %
b110 +
b110111101011 #
b110111101011 *
b1110 )
#150000
b110000101110010011010010111010001101000001000000111001101101000011010010110011001110100 /
b111001001101001011001110110100001110100 -
0!
b0 "
b0 .
b1 &
b1 ,
1$
b1010 %
b1010 +
b1010111100 #
b1010111100 *
b1111 )
#160000
b11100100110111101110100011000010111010001100101 /
b1000001100001010 "
b1000001100001010 .
b10 &
b10 ,
b1111 %
b1111 +
b100000110000101 #
b100000110000101 *
b10000 )
#170000
b110000101110010011010010111010001101000001000000111001101101000011010010110011001110100 /
b110010011 "
b110010011 .
b1 &
b1 ,
b101 %
b101 +
b11001001111110 #
b11001001111110 *
b10001 )
#180000
b0 "
b0 .
b11 &
b11 ,
b1100 %
b1100 +
b11101100010 #
b11101100010 *
b10010 )
#190000
b1101100011011110110011101101001011000110110000101101100001000000111001101101000011010010110011001110100 /
b101010011 "
b101010011 .
b0 &
b0 ,
b111 %
b111 +
b1010100111111000 #
b1010100111111000 *
b10011 )
#200000
b1100000 "
b1100000 .
b1001 %
b1001 +
b1100000001011011 #
b1100000001011011 *
b10100 )
#210000
b1101100011001010110011001110100 -
1!
b1000000110101110 "
b1000000110101110 .
0$
b1 %
b1 +
b1100000011010111 #
b1100000011010111 *
b10101 )
#220000
b110000101110010011010010111010001101000001000000111001101101000011010010110011001110100 /
b111001001101001011001110110100001110100 -
0!
b11001110 "
b11001110 .
b1 &
b1 ,
1$
b1000 %
b1000 +
b1100111011000010 #
b1100111011000010 *
b10110 )
#230000
b11 "
b11 .
b1110 %
b1110 +
b1101101100010010 #
b1101101100010010 *
b10111 )
#240000
b1101100011011110110011101101001011000110110000101101100001000000111001101101000011010010110011001110100 /
b1000111100011 "
b1000111100011 .
b0 &
b0 ,
b11 %
b11 +
b1000111100011111 #
b1000111100011111 *
b11000 )
#250000
b11100100110111101110100011000010111010001100101 /
b1010110110101100 "
b1010110110101100 .
b10 &
b10 ,
b1001 %
b1001 +
b101100101011011 #
b101100101011011 *
b11001 )
#260000
b1101100011011110110011101101001011000110110000101101100001000000111001101101000011010010110011001110100 /
b1101100011001010110011001110100 -
b1101011000000000 "
b1101011000000000 .
b0 &
b0 ,
0$
b110 %
b110 +
b110001101011000 #
b110001101011000 *
b11010 )
#270000
b111001001101001011001110110100001110100 -
b0 "
b0 .
b11 &
b11 ,
1$
b1001100111111010 #
b1001100111111010 *
b11011 )
#280000
b1010100000101 "
b1010100000101 .
b0 &
b0 ,
b11 %
b11 +
b1010100000101111 #
b1010100000101111 *
b11100 )
#290000
b11100100110111101110100011000010111010001100101 /
b1101100011001010110011001110100 -
b1011111111101111 "
b1011111111101111 .
b10 &
b10 ,
0$
b1011 %
b1011 +
b1111110111110111 #
b1111110111110111 *
b11101 )
#300000
b110000101110010011010010111010001101000001000000111001101101000011010010110011001110100 /
1!
b10000000000000 "
b10000000000000 .
b1 &
b1 ,
b1101 %
b1101 +
b1100000100101001 #
b1100000100101001 *
b11110 )
#310000
b1101100011011110110011101101001011000110110000101101100001000000111001101101000011010010110011001110100 /
b111001001101001011001110110100001110100 -
0!
b1 "
b1 .
b0 &
b0 ,
1$
b1111 %
b1111 +
b1110001010110101 #
b1110001010110101 *
b11111 )
#320000
b11100100110111101110100011000010111010001100101 /
b11010000000011 "
b11010000000011 .
b10 &
b10 ,
b1010 %
b1010 +
b110011010000 #
b110011010000 *
b100000 )
#330000
b0 "
b0 .
b11 &
b11 ,
b1010110111011100 #
b1010110111011100 *
b100001 )
#340000
b1011010101011011 "
b1011010101011011 .
b10 &
b10 ,
b1110 %
b1110 +
b1110110101010110 #
b1110110101010110 *
b100010 )
#350000
b1101100011011110110011101101001011000110110000101101100001000000111001101101000011010010110011001110100 /
b10111001 "
b10111001 .
b0 &
b0 ,
b1000 %
b1000 +
b1011100110110110 #
b1011100110110110 *
b100011 )
#360000
b110000101110010011010010111010001101000001000000111001101101000011010010110011001110100 /
b1101100011001010110011001110100 -
1!
b1111110010100000 "
b1111110010100000 .
b1 &
b1 ,
0$
b11 %
b11 +
b1011111110010100 #
b1011111110010100 *
b100100 )
#370000
b111001001101001011001110110100001110100 -
0!
b11 "
b11 .
1$
b1101 %
b1101 +
b110100111011011 #
b110100111011011 *
b100101 )
#380000
b1101100011001010110011001110100 -
1!
b1101100000000000 "
b1101100000000000 .
0$
b1010 %
b1010 +
b1110001001110110 #
b1110001001110110 *
b100110 )
#390000
b111001001101001011001110110100001110100 -
0!
b110100100 "
b110100100 .
1$
b100 %
b100 +
b1101001000110 #
b1101001000110 *
b100111 )
#400000
b1101100011001010110011001110100 -
b1011010000000000 "
b1011010000000000 .
0$
b1000 %
b1000 +
b1011101010110100 #
b1011101010110100 *
b101000 )
#410000
b1101100011011110110011101101001011000110110000101101100001000000111001101101000011010010110011001110100 /
1!
b1100000000000000 "
b1100000000000000 .
b0 &
b0 ,
b1110 %
b1110 +
b11000011000111 #
b11000011000111 *
b101001 )
#420000
b11100100110111101110100011000010111010001100101 /
b1111101101001101 "
b1111101101001101 .
b10 &
b10 ,
b1001 %
b1001 +
b1010011011111101 #
b1010011011111101 *
b101010 )
#430000
b1101100011011110110011101101001011000110110000101101100001000000111001101101000011010010110011001110100 /
b100000000000000 "
b100000000000000 .
b0 &
b0 ,
b1101 %
b1101 +
b100011011010 #
b100011011010 *
b101011 )
#440000
b11100100110111101110100011000010111010001100101 /
b1100110000010001 "
b1100110000010001 .
b10 &
b10 ,
b1010 %
b1010 +
b10001110011 #
b10001110011 *
b101100 )
#450000
b111001001101001011001110110100001110100 -
b0 "
b0 .
b11 &
b11 ,
1$
b10111010101 #
b10111010101 *
b101101 )
#460000
b1101100011001010110011001110100 -
b11011110010110 "
b11011110010110 .
b10 &
b10 ,
0$
b0 %
b0 +
b11011110010110 #
b11011110010110 *
b101110 )
#470000
b1101100011011110110011101101001011000110110000101101100001000000111001101101000011010010110011001110100 /
b1101000000000000 "
b1101000000000000 .
b0 &
b0 ,
b1100 %
b1100 +
b1000001101111101 #
b1000001101111101 *
b101111 )
#480000
b110000101110010011010010111010001101000001000000111001101101000011010010110011001110100 /
b111001001101001011001110110100001110100 -
0!
b10011 "
b10011 .
b1 &
b1 ,
1$
b1011 %
b1011 +
b1001101101111110 #
b1001101101111110 *
b110000 )
#490000
b111001001111101 "
b111001001111101 .
b1 %
b1 +
b1110010011111010 #
b1110010011111010 *
b110001 )
#500000
b110010 )
