projects/zaram_training_course/03_sequential_logic/06_sram/spsram.v
module spsram
#(
	parameter	BW_DATA = 32,
	parameter	BW_ADDR = 5
)
(
	input clk,
	input wen,
	input cen,
	input oen,
	input [BW_ADDR-1:0] addr,
	input [BW_DATA-1:0] i_data,
	output [BW_DATA-1:0] o_data
);

	// Memory Write
	reg		[BW_DATA-1:0]	mem[0:2**BW_ADDR-1];
	always @ (posedge clk) begin
		if(cen && wen)
			mem[addr] <= i_data;
		else
			mem[addr] <= mem[addr];
	end

	// Memory Read
	`ifdef	SPSRAM_ASYNC
		assign o_data = !oen ? 'bz :
						cen && !wen ? mem[addr] : 'bx;
	`else //sync
		reg		[BW_DATA-1:0] o_data;
		always @ (posedge clk) begin
			if(oen) begin
				if(cen && !wen)
					o_data <= mem[addr];
				else
					o_data <= 'bx;
			end
			else
				o_data <= 'bz;
		end
	`endif

endmodule

projects/zaram_training_course/03_sequential_logic/06_sram/sram_doubled.v
// ==================================================
//	[ VLSISYS Lab. ]
//	* Author		: HyeRyun Lim (imh2880@gmail.com)
//	* Filename		: sram_doubled.v
//	* Date			: 2024-06-26 17:32:36
//	* Description	: 
//	00000
//	~
//	01111
//
//	10000
//	~
//	11111
//	only addr[4] is different.
// ==================================================

`include "spsram.v"
module sram_doubled
#(
	parameter	BW_DATA = 32,
	parameter	BW_ADDR = 5
)
(
	input clk,
	input wen,
	input cen,
	input oen,
	input [BW_ADDR-1:0] addr,
	input [BW_DATA-1:0] i_data,
	output [BW_DATA-1:0] o_data
);
	spsram
	#(
		.BW_DATA			(32			),
		.BW_ADDR			(4			)
	)
	u_spsram0(
		.clk				(clk				),
		.wen				(wen				),
		.cen				(~addr[4]			),
		.oen				(~addr[4]			),
		.addr				(addr[3:0]			),
		.i_data				(i_data				),
		.o_data				(o_data				)
	);

	spsram
	#(
		.BW_DATA			(32			),
		.BW_ADDR			(4			)
	)
	u_spsram1(
		.clk				(clk				),
		.wen				(wen				),
		.cen				(addr[4]			),
		.oen				(addr[4]			),
		.addr				(addr[3:0]			),
		.i_data				(i_data				),
		.o_data				(o_data				)
	);
endmodule

projects/zaram_training_course/03_sequential_logic/06_sram/sram_doubled_tb.v
// --------------------------------------------------
//	Define Global Variables
// --------------------------------------------------
`define	CLKFREQ		100		// Clock Freq. (Unit: MHz)
`define	SIMCYCLE	`NVEC	// Sim. Cycles
`define NVEC		32		// # of Test Vector
//`define SPSRAM_ASYNC

// --------------------------------------------------
//	Includes
// --------------------------------------------------
`include	"sram_doubled.v"

module sram_doubled_tb;
// --------------------------------------------------
//	DUT Signals & Instantiate
// --------------------------------------------------
	reg clk;
	reg wen;
	reg cen;
	reg oen;
	reg [BW_ADDR-1:0] addr;
	reg [BW_DATA-1:0] i_data;
	wire [BW_DATA-1:0] o_data;

	parameter BW_DATA = 32;
	parameter BW_ADDR = 5;

	sram_doubled
	#(
		.BW_DATA			(BW_DATA			),
		.BW_ADDR			(BW_ADDR			)
	)
	u_sram_doubled(
		.clk				(clk				),
		.wen				(wen				),
		.cen				(cen				),
		.oen				(oen				),
		.addr				(addr				),
		.i_data				(i_data				),
		.o_data				(o_data				)
	);


// --------------------------------------------------
//	Tasks
// --------------------------------------------------
	reg [8*32-1:0] taskState;
	integer err = 0;

	task init;
		begin
			taskState = "Init";
			clk		= 0;
			wen		= 0;
			cen 	= 0;
			oen		= 0;
			addr	= 0;
			i_data	= 0;
		end
	endtask

	task memWR;
		input	[BW_ADDR-1:0] t_addr;
		input	[BW_DATA-1:0] t_data;
		begin
			@(negedge clk) begin
				taskState = "WR";
				i_data = t_data;
				addr = t_addr;
				cen	 = 1;
				wen  = 1;
				oen  = 0;
			end
		end
	endtask

	task memRD;
		input	[BW_ADDR-1:0] t_addr;
		begin
			@(negedge clk) begin
				taskState = "RD";
				addr = t_addr;
				cen = 1;
				wen = 0;
				oen = 1;
			end
		end
	endtask


	always #(500/`CLKFREQ) clk = ~clk;

// --------------------------------------------------
//	Test Stimulus
// --------------------------------------------------
	integer		i, j;
	initial begin
		init();
		#(4*1000/`CLKFREQ);

		for (i=0; i<`SIMCYCLE; i++) begin
			memWR(i, i);
		end
		for (i=0; i<`SIMCYCLE; i++) begin
			memRD(i);
		end
		$finish;
	end

// --------------------------------------------------
//	Dump VCD
// --------------------------------------------------
	reg	[8*32-1:0]	vcd_file;
	initial begin
		if ($value$plusargs("vcd_file=%s", vcd_file)) begin
			$dumpfile(vcd_file);
			$dumpvars;
		end else begin
			$dumpfile("sram_doubled_tb.vcd");
			$dumpvars;
		end
	end

endmodule

projects/zaram_training_course/03_sequential_logic/06_sram/vcd/sram_doubled.vcd
$date
	Mon Jul  1 11:05:15 2024
$end
$version
	Icarus Verilog
$end
$timescale
	1ps
$end
$scope module sram_doubled_tb $end
$var wire 32 ! o_data [31:0] $end
$var reg 5 " addr [4:0] $end
$var reg 1 # cen $end
$var reg 1 $ clk $end
$var reg 32 % i_data [31:0] $end
$var reg 1 & oen $end
$var reg 256 ' taskState [255:0] $end
$var reg 256 ( vcd_file [255:0] $end
$var reg 1 ) wen $end
$var integer 32 * err [31:0] $end
$var integer 32 + i [31:0] $end
$scope module u_sram_doubled $end
$var wire 5 , addr [4:0] $end
$var wire 1 # cen $end
$var wire 1 $ clk $end
$var wire 32 - i_data [31:0] $end
$var wire 32 . o_data [31:0] $end
$var wire 1 & oen $end
$var wire 1 ) wen $end
$scope module u_spsram0 $end
$var wire 4 / addr [3:0] $end
$var wire 1 0 cen $end
$var wire 1 $ clk $end
$var wire 32 1 i_data [31:0] $end
$var wire 1 2 oen $end
$var wire 1 ) wen $end
$var reg 32 3 o_data [31:0] $end
$upscope $end
$scope module u_spsram1 $end
$var wire 4 4 addr [3:0] $end
$var wire 1 5 cen $end
$var wire 1 $ clk $end
$var wire 32 6 i_data [31:0] $end
$var wire 1 7 oen $end
$var wire 1 ) wen $end
$var reg 32 8 o_data [31:0] $end
$upscope $end
$upscope $end
$scope task init $end
$upscope $end
$scope task memRD $end
$var reg 5 9 t_addr [4:0] $end
$upscope $end
$scope task memWR $end
$var reg 5 : t_addr [4:0] $end
$var reg 32 ; t_data [31:0] $end
$upscope $end
$upscope $end
$enddefinitions $end
#0
$dumpvars
bx ;
bx :
bx 9
bx 8
07
b0 6
05
b0 4
bx 3
12
b0 1
10
b0 /
bx .
b0 -
b0 ,
bx +
b0 *
0)
b101110001011110111011001100011011001000010111101110011011100100110000101101101010111110110010001101111011101010110001001101100011001010110010000101110011101100110001101100100 (
b1001001011011100110100101110100 '
0&
b0 %
0$
0#
b0 "
bx !
$end
#5000
bz 8
1$
#10000
0$
#15000
1$
#20000
0$
#25000
1$
#30000
0$
#35000
1$
#40000
1)
1#
b101011101010010 '
0$
b1 ;
b1 :
b1 +
#45000
1$
#50000
b1 /
b1 4
b10 ;
b10 :
b10 +
b1 "
b1 ,
b1 %
b1 -
b1 1
b1 6
0$
#55000
1$
#60000
b10 /
b10 4
b11 ;
b11 :
b11 +
b10 "
b10 ,
b10 %
b10 -
b10 1
b10 6
0$
#65000
1$
#70000
b11 /
b11 4
b100 ;
b100 :
b100 +
b11 "
b11 ,
b11 %
b11 -
b11 1
b11 6
0$
#75000
1$
#80000
b100 /
b100 4
b101 ;
b101 :
b101 +
b100 "
b100 ,
b100 %
b100 -
b100 1
b100 6
0$
#85000
1$
#90000
b101 /
b101 4
b110 ;
b110 :
b110 +
b101 "
b101 ,
b101 %
b101 -
b101 1
b101 6
0$
#95000
1$
#100000
b110 /
b110 4
b111 ;
b111 :
b111 +
b110 "
b110 ,
b110 %
b110 -
b110 1
b110 6
0$
#105000
1$
#110000
b111 /
b111 4
b1000 ;
b1000 :
b1000 +
b111 "
b111 ,
b111 %
b111 -
b111 1
b111 6
0$
#115000
1$
#120000
b1000 /
b1000 4
b1001 ;
b1001 :
b1001 +
b1000 "
b1000 ,
b1000 %
b1000 -
b1000 1
b1000 6
0$
#125000
1$
#130000
b1001 /
b1001 4
b1010 ;
b1010 :
b1010 +
b1001 "
b1001 ,
b1001 %
b1001 -
b1001 1
b1001 6
0$
#135000
1$
#140000
b1010 /
b1010 4
b1011 ;
b1011 :
b1011 +
b1010 "
b1010 ,
b1010 %
b1010 -
b1010 1
b1010 6
0$
#145000
1$
#150000
b1011 /
b1011 4
b1100 ;
b1100 :
b1100 +
b1011 "
b1011 ,
b1011 %
b1011 -
b1011 1
b1011 6
0$
#155000
1$
#160000
b1100 /
b1100 4
b1101 ;
b1101 :
b1101 +
b1100 "
b1100 ,
b1100 %
b1100 -
b1100 1
b1100 6
0$
#165000
1$
#170000
b1101 /
b1101 4
b1110 ;
b1110 :
b1110 +
b1101 "
b1101 ,
b1101 %
b1101 -
b1101 1
b1101 6
0$
#175000
1$
#180000
b1110 /
b1110 4
b1111 ;
b1111 :
b1111 +
b1110 "
b1110 ,
b1110 %
b1110 -
b1110 1
b1110 6
0$
#185000
1$
#190000
b1111 /
b1111 4
b10000 ;
b10000 :
b10000 +
b1111 "
b1111 ,
b1111 %
b1111 -
b1111 1
b1111 6
0$
#195000
1$
#200000
00
02
b0 /
15
17
b0 4
b10001 ;
b10001 :
b10001 +
b10000 "
b10000 ,
b10000 %
b10000 -
b10000 1
b10000 6
0$
#205000
bz 3
bx 8
1$
#210000
b1 /
b1 4
b10010 ;
b10010 :
b10010 +
b10001 "
b10001 ,
b10001 %
b10001 -
b10001 1
b10001 6
0$
#215000
1$
#220000
b10 /
b10 4
b10011 ;
b10011 :
b10011 +
b10010 "
b10010 ,
b10010 %
b10010 -
b10010 1
b10010 6
0$
#225000
1$
#230000
b11 /
b11 4
b10100 ;
b10100 :
b10100 +
b10011 "
b10011 ,
b10011 %
b10011 -
b10011 1
b10011 6
0$
#235000
1$
#240000
b100 /
b100 4
b10101 ;
b10101 :
b10101 +
b10100 "
b10100 ,
b10100 %
b10100 -
b10100 1
b10100 6
0$
#245000
1$
#250000
b101 /
b101 4
b10110 ;
b10110 :
b10110 +
b10101 "
b10101 ,
b10101 %
b10101 -
b10101 1
b10101 6
0$
#255000
1$
#260000
b110 /
b110 4
b10111 ;
b10111 :
b10111 +
b10110 "
b10110 ,
b10110 %
b10110 -
b10110 1
b10110 6
0$
#265000
1$
#270000
b111 /
b111 4
b11000 ;
b11000 :
b11000 +
b10111 "
b10111 ,
b10111 %
b10111 -
b10111 1
b10111 6
0$
#275000
1$
#280000
b1000 /
b1000 4
b11001 ;
b11001 :
b11001 +
b11000 "
b11000 ,
b11000 %
b11000 -
b11000 1
b11000 6
0$
#285000
1$
#290000
b1001 /
b1001 4
b11010 ;
b11010 :
b11010 +
b11001 "
b11001 ,
b11001 %
b11001 -
b11001 1
b11001 6
0$
#295000
1$
#300000
b1010 /
b1010 4
b11011 ;
b11011 :
b11011 +
b11010 "
b11010 ,
b11010 %
b11010 -
b11010 1
b11010 6
0$
#305000
1$
#310000
b1011 /
b1011 4
b11100 ;
b11100 :
b11100 +
b11011 "
b11011 ,
b11011 %
b11011 -
b11011 1
b11011 6
0$
#315000
1$
#320000
b1100 /
b1100 4
b11101 ;
b11101 :
b11101 +
b11100 "
b11100 ,
b11100 %
b11100 -
b11100 1
b11100 6
0$
#325000
1$
#330000
b1101 /
b1101 4
b11110 ;
b11110 :
b11110 +
b11101 "
b11101 ,
b11101 %
b11101 -
b11101 1
b11101 6
0$
#335000
1$
#340000
b1110 /
b1110 4
b11111 ;
b11111 :
b11111 +
b11110 "
b11110 ,
b11110 %
b11110 -
b11110 1
b11110 6
0$
#345000
1$
#350000
b1111 /
b1111 4
b0 9
b0 +
b11111 "
b11111 ,
b11111 %
b11111 -
b11111 1
b11111 6
0$
#355000
1$
#360000
10
12
b0 /
05
07
b0 4
b1 9
b1 +
1&
0)
b0 "
b0 ,
b101001001000100 '
0$
#365000
b0 3
b0 !
b0 .
bz 8
1$
#370000
b1 /
b1 4
b10 9
b10 +
b1 "
b1 ,
0$
#375000
b1 !
b1 .
b1 3
1$
#380000
b10 /
b10 4
b11 9
b11 +
b10 "
b10 ,
0$
#385000
b10 !
b10 .
b10 3
1$
#390000
b11 /
b11 4
b100 9
b100 +
b11 "
b11 ,
0$
#395000
b11 !
b11 .
b11 3
1$
#400000
b100 /
b100 4
b101 9
b101 +
b100 "
b100 ,
0$
#405000
b100 !
b100 .
b100 3
1$
#410000
b101 /
b101 4
b110 9
b110 +
b101 "
b101 ,
0$
#415000
b101 !
b101 .
b101 3
1$
#420000
b110 /
b110 4
b111 9
b111 +
b110 "
b110 ,
0$
#425000
b110 !
b110 .
b110 3
1$
#430000
b111 /
b111 4
b1000 9
b1000 +
b111 "
b111 ,
0$
#435000
b111 !
b111 .
b111 3
1$
#440000
b1000 /
b1000 4
b1001 9
b1001 +
b1000 "
b1000 ,
0$
#445000
b1000 !
b1000 .
b1000 3
1$
#450000
b1001 /
b1001 4
b1010 9
b1010 +
b1001 "
b1001 ,
0$
#455000
b1001 !
b1001 .
b1001 3
1$
#460000
b1010 /
b1010 4
b1011 9
b1011 +
b1010 "
b1010 ,
0$
#465000
b1010 !
b1010 .
b1010 3
1$
#470000
b1011 /
b1011 4
b1100 9
b1100 +
b1011 "
b1011 ,
0$
#475000
b1011 !
b1011 .
b1011 3
1$
#480000
b1100 /
b1100 4
b1101 9
b1101 +
b1100 "
b1100 ,
0$
#485000
b1100 !
b1100 .
b1100 3
1$
#490000
b1101 /
b1101 4
b1110 9
b1110 +
b1101 "
b1101 ,
0$
#495000
b1101 !
b1101 .
b1101 3
1$
#500000
b1110 /
b1110 4
b1111 9
b1111 +
b1110 "
b1110 ,
0$
#505000
b1110 !
b1110 .
b1110 3
1$
#510000
b1111 /
b1111 4
b10000 9
b10000 +
b1111 "
b1111 ,
0$
#515000
b1111 !
b1111 .
b1111 3
1$
#520000
00
02
b0 /
15
17
b0 4
b10001 9
b10001 +
b10000 "
b10000 ,
0$
#525000
bz 3
b10000 !
b10000 .
b10000 8
1$
#530000
b1 /
b1 4
b10010 9
b10010 +
b10001 "
b10001 ,
0$
#535000
b10001 !
b10001 .
b10001 8
1$
#540000
b10 /
b10 4
b10011 9
b10011 +
b10010 "
b10010 ,
0$
#545000
b10010 !
b10010 .
b10010 8
1$
#550000
b11 /
b11 4
b10100 9
b10100 +
b10011 "
b10011 ,
0$
#555000
b10011 !
b10011 .
b10011 8
1$
#560000
b100 /
b100 4
b10101 9
b10101 +
b10100 "
b10100 ,
0$
#565000
b10100 !
b10100 .
b10100 8
1$
#570000
b101 /
b101 4
b10110 9
b10110 +
b10101 "
b10101 ,
0$
#575000
b10101 !
b10101 .
b10101 8
1$
#580000
b110 /
b110 4
b10111 9
b10111 +
b10110 "
b10110 ,
0$
#585000
b10110 !
b10110 .
b10110 8
1$
#590000
b111 /
b111 4
b11000 9
b11000 +
b10111 "
b10111 ,
0$
#595000
b10111 !
b10111 .
b10111 8
1$
#600000
b1000 /
b1000 4
b11001 9
b11001 +
b11000 "
b11000 ,
0$
#605000
b11000 !
b11000 .
b11000 8
1$
#610000
b1001 /
b1001 4
b11010 9
b11010 +
b11001 "
b11001 ,
0$
#615000
b11001 !
b11001 .
b11001 8
1$
#620000
b1010 /
b1010 4
b11011 9
b11011 +
b11010 "
b11010 ,
0$
#625000
b11010 !
b11010 .
b11010 8
1$
#630000
b1011 /
b1011 4
b11100 9
b11100 +
b11011 "
b11011 ,
0$
#635000
b11011 !
b11011 .
b11011 8
1$
#640000
b1100 /
b1100 4
b11101 9
b11101 +
b11100 "
b11100 ,
0$
#645000
b11100 !
b11100 .
b11100 8
1$
#650000
b1101 /
b1101 4
b11110 9
b11110 +
b11101 "
b11101 ,
0$
#655000
b11101 !
b11101 .
b11101 8
1$
#660000
b1110 /
b1110 4
b11111 9
b11111 +
b11110 "
b11110 ,
0$
#665000
b11110 !
b11110 .
b11110 8
1$
#670000
b1111 /
b1111 4
b100000 +
b11111 "
b11111 ,
0$
