projects/verilog_tutorials/project_0/04_shift_register/shift_register.v
module shift_register
#(
	parameter bit_size = 8
)
(
	input clk,
	input load,
	input Sin,
	input [bit_size-1:0] d,
	output [bit_size-1:0] q,
	output Sout
);

		mux_dff
		u_mux_dff(
			.clk				(clk				),
			.load				(load				),
			.Sin				(Sin				),
			.d					(d[0]				),
			.q					(q[0]				)
		);
	genvar i;
	generate
		for (i=1; i<bit_size; i=i+1) begin : shift_register_block
			mux_dff
			u_mux_dff(
				.clk				(clk				),
				.load				(load				),
				.Sin				(q[i-1]				),
				.d					(d[i]				),
				.q					(q[i]				)
			);
		end

		assign Sout = q[7];
	endgenerate
	
endmodule

module mux_dff
(
	input clk,
	input load,
	input Sin,
	input d,
	output reg q,
	output reg Sout
);

	reg mux_out;

	always @ (*) begin
		case(load)
			0 : mux_out = Sin;
			1 : mux_out = d;
		endcase
	end

	always @ (posedge clk) begin
		q <= mux_out;
	end

endmodule

projects/verilog_tutorials/project_0/04_shift_register/shift_register_tb.v
// --------------------------------------------------
//	Define Global Variables
// --------------------------------------------------
`define	CLKFREQ		100		// Clock Freq. (Unit: MHz)
`define	SIMCYCLE	`NVEC	// Sim. Cycles
`define NVEC		50		// # of Test Vector

// --------------------------------------------------
//	Includes
// --------------------------------------------------
`include	"shift_register.v"

module shift_register_tb;
// --------------------------------------------------
//	DUT Signals & Instantiate
// --------------------------------------------------
	parameter bit_size = 8;

	reg clk;
	reg load;
	reg Sin;
	reg [bit_size-1:0] d;
	wire [bit_size-1:0] q;
	wire Sout;

	shift_register
	#(
		.bit_size			(bit_size			)
	)
	u_shift_register(
		.clk				(clk				),
		.load				(load				),
		.Sin				(Sin				),
		.d					(d					),
		.q					(q					),
		.Sout				(Sout				)
	);



// --------------------------------------------------
//	Tasks
// --------------------------------------------------
	reg [8*32-1:0] taskState;
	integer err = 0;

	task init;
		begin
			taskState = "Init";
			clk = 0;
			load = 0;
			Sin = 0;
			d = 0;
		end
	endtask

	always #(500/`CLKFREQ) clk = ~clk;

// --------------------------------------------------
//	Test Stimulus
// --------------------------------------------------
	integer		i, j;
	initial begin
		init();

		for (i=0; i<`SIMCYCLE; i++) begin
			load = $urandom;
			Sin  = $urandom;
			d = $urandom;
			#(1000/`CLKFREQ);
		end
		$finish;
	end

// --------------------------------------------------
//	Dump VCD
// --------------------------------------------------
	reg	[8*32-1:0]	vcd_file;
	initial begin
		if ($value$plusargs("vcd_file=%s", vcd_file)) begin
			$dumpfile(vcd_file);
			$dumpvars;
		end else begin
			$dumpfile("shift_register_tb.vcd");
			$dumpvars;
		end
	end

endmodule

projects/verilog_tutorials/project_0/04_shift_register/vcd/shift_register.vcd
$date
	Mon Jul  1 13:31:59 2024
$end
$version
	Icarus Verilog
$end
$timescale
	1ps
$end
$scope module shift_register_tb $end
$var wire 8 ! q [7:0] $end
$var wire 1 " Sout $end
$var reg 1 # Sin $end
$var reg 1 $ clk $end
$var reg 8 % d [7:0] $end
$var reg 1 & load $end
$var reg 256 ' taskState [255:0] $end
$var reg 256 ( vcd_file [255:0] $end
$var integer 32 ) err [31:0] $end
$var integer 32 * i [31:0] $end
$scope module u_shift_register $end
$var wire 1 # Sin $end
$var wire 1 $ clk $end
$var wire 8 + d [7:0] $end
$var wire 1 & load $end
$var wire 8 , q [7:0] $end
$var wire 1 " Sout $end
$scope begin shift_register_block[1] $end
$scope module u_mux_dff $end
$var wire 1 - Sin $end
$var wire 1 $ clk $end
$var wire 1 . d $end
$var wire 1 & load $end
$var reg 1 / Sout $end
$var reg 1 0 mux_out $end
$var reg 1 1 q $end
$upscope $end
$upscope $end
$scope begin shift_register_block[2] $end
$scope module u_mux_dff $end
$var wire 1 2 Sin $end
$var wire 1 $ clk $end
$var wire 1 3 d $end
$var wire 1 & load $end
$var reg 1 4 Sout $end
$var reg 1 5 mux_out $end
$var reg 1 6 q $end
$upscope $end
$upscope $end
$scope begin shift_register_block[3] $end
$scope module u_mux_dff $end
$var wire 1 7 Sin $end
$var wire 1 $ clk $end
$var wire 1 8 d $end
$var wire 1 & load $end
$var reg 1 9 Sout $end
$var reg 1 : mux_out $end
$var reg 1 ; q $end
$upscope $end
$upscope $end
$scope begin shift_register_block[4] $end
$scope module u_mux_dff $end
$var wire 1 < Sin $end
$var wire 1 $ clk $end
$var wire 1 = d $end
$var wire 1 & load $end
$var reg 1 > Sout $end
$var reg 1 ? mux_out $end
$var reg 1 @ q $end
$upscope $end
$upscope $end
$scope begin shift_register_block[5] $end
$scope module u_mux_dff $end
$var wire 1 A Sin $end
$var wire 1 $ clk $end
$var wire 1 B d $end
$var wire 1 & load $end
$var reg 1 C Sout $end
$var reg 1 D mux_out $end
$var reg 1 E q $end
$upscope $end
$upscope $end
$scope begin shift_register_block[6] $end
$scope module u_mux_dff $end
$var wire 1 F Sin $end
$var wire 1 $ clk $end
$var wire 1 G d $end
$var wire 1 & load $end
$var reg 1 H Sout $end
$var reg 1 I mux_out $end
$var reg 1 J q $end
$upscope $end
$upscope $end
$scope begin shift_register_block[7] $end
$scope module u_mux_dff $end
$var wire 1 K Sin $end
$var wire 1 $ clk $end
$var wire 1 L d $end
$var wire 1 & load $end
$var reg 1 M Sout $end
$var reg 1 N mux_out $end
$var reg 1 O q $end
$upscope $end
$upscope $end
$scope module u_mux_dff $end
$var wire 1 # Sin $end
$var wire 1 $ clk $end
$var wire 1 P d $end
$var wire 1 & load $end
$var reg 1 Q Sout $end
$var reg 1 R mux_out $end
$var reg 1 S q $end
$upscope $end
$upscope $end
$scope task init $end
$upscope $end
$upscope $end
$enddefinitions $end
#0
$dumpvars
xS
1R
xQ
1P
xO
xN
xM
0L
xK
xJ
xI
xH
0G
xF
xE
xD
xC
0B
xA
x@
x?
x>
0=
x<
x;
x:
x9
18
x7
x6
x5
x4
03
x2
x1
x0
x/
0.
x-
bx ,
b1001 +
b0 *
b0 )
b1011100010111101110110011000110110010000101111011100110110100001101001011001100111010001011111011100100110010101100111011010010111001101110100011001010111001000101110011101100110001101100100 (
b1001001011011100110100101110100 '
0&
b1001 %
0$
1#
x"
bx !
$end
#5000
10
1-
bx1 !
bx1 ,
1S
1$
#10000
13
1L
00
15
1:
0?
0D
0I
1N
0$
b10001101 %
b10001101 +
1&
b1 *
#15000
1"
0K
0F
0A
1<
17
02
1O
0J
0E
0@
1;
16
b10001101 !
b10001101 ,
01
1$
#20000
05
0:
0N
03
08
0L
0$
b1 %
b1 +
0#
b10 *
#25000
07
0<
0"
06
0;
b1 !
b1 ,
0O
1$
#30000
15
1:
1?
1D
13
18
1=
1B
0$
b111101 %
b111101 +
b11 *
#35000
1F
1A
1<
17
1E
1@
1;
b111101 !
b111101 ,
16
1$
#40000
05
1I
1N
03
1G
1L
0$
b11111001 %
b11111001 +
b100 *
#45000
07
1K
1"
06
1J
b11111001 !
b11111001 ,
1O
1$
#50000
1.
0=
0G
0P
10
0:
0$
b10101010 %
b10101010 +
1#
0&
b101 *
#55000
0?
15
0<
12
0;
b11110011 !
b11110011 ,
11
1$
#60000
1?
0D
0N
08
1=
0B
0L
05
0:
0I
0R
0$
b10010 %
b10010 +
1&
b110 *
#65000
0F
0K
0"
0-
0E
0J
0O
b10010 !
b10010 ,
0S
1$
#70000
15
1:
0?
1I
1N
13
18
0=
1G
1L
0$
b11001110 %
b11001110 +
0#
b111 *
#75000
1"
1K
0A
1<
17
1O
1J
0@
1;
b11001110 !
b11001110 ,
16
1$
#80000
0.
1=
0L
00
1?
0I
1R
0$
b1011100 %
b1011100 +
1#
0&
b1000 *
#85000
05
1D
0N
10
02
1A
0K
1-
01
1@
0J
b10011101 !
b10011101 ,
1S
1$
#90000
0:
0?
08
0=
1B
1P
00
15
1D
1I
1R
0$
b1100101 %
b1100101 +
1&
b1001 *
#95000
0"
1K
1F
0A
0<
0O
1J
1E
0@
b1100101 !
b1100101 ,
0;
1$
#100000
05
0D
0I
1N
0R
03
0B
0G
1L
0P
0$
b10000000 %
b10000000 +
0#
b1010 *
#105000
07
0F
0K
1"
0-
06
0E
0J
1O
b10000000 !
b10000000 ,
0S
1$
#110000
13
18
1=
1P
0N
0$
b10011101 %
b10011101 +
0&
b1011 *
#115000
0"
b0 !
b0 ,
0O
1$
#120000
0=
0L
1R
0$
b1101 %
b1101 +
1#
b1100 *
#125000
10
1-
b1 !
b1 ,
1S
1$
#130000
1?
1I
1N
08
1=
1G
1L
00
15
0:
0$
b11010101 %
b11010101 +
1&
b1101 *
#135000
1"
1K
1A
17
1O
1J
1@
b11010101 !
b11010101 ,
16
1$
#140000
18
0G
0L
10
05
1:
0?
1D
0I
0R
0$
b11101 %
b11101 +
0#
0&
b1110 *
#145000
15
0:
1?
0D
1I
0N
00
12
07
1<
0A
1F
0K
0-
11
06
1;
0@
1E
0J
b10101010 !
b10101010 ,
0S
1$
#150000
10
05
0?
1.
03
0=
0P
1:
0I
0R
0$
b1010 %
b1010 +
1#
1&
b1111 *
#155000
0"
0F
0O
b1010 !
b1010 ,
0E
1$
#160000
08
1=
1B
1G
1L
00
15
0:
1?
0$
b11110010 %
b11110010 +
0#
0&
b10000 *
#165000
05
1:
0?
1D
02
17
0<
1A
01
16
0;
b10100 !
b10100 ,
1@
1$
#170000
0.
18
0B
1R
0$
b11011000 %
b11011000 +
1#
b10001 *
#175000
10
1I
0D
1?
0:
1-
1F
0A
1<
07
1S
1E
0@
1;
b101001 !
b101001 ,
06
1$
#180000
1.
0=
1B
1P
0$
b11101011 %
b11101011 +
b10010 *
#185000
15
0?
1D
0I
1N
12
0<
1A
0F
1K
11
0;
1@
0E
b1010011 !
b1010011 ,
1J
1$
#190000
13
0G
0P
0R
0$
b10101110 %
b10101110 +
0#
b10011 *
#195000
00
0N
1I
0D
1:
0-
1"
0K
1F
0A
17
0S
1O
0J
1E
0@
b10100110 !
b10100110 ,
16
1$
#200000
03
0B
0L
1P
0$
b1011 %
b1011 +
b10100 *
#205000
05
1?
0I
1N
02
1<
0F
1K
0"
01
1;
0E
1J
b1001100 !
b1001100 ,
0O
1$
#210000
15
1I
13
1G
10
0?
0N
1R
0$
b1001111 %
b1001111 +
1#
1&
b10101 *
#215000
1-
12
1S
b1001111 !
b1001111 ,
11
1$
#220000
1?
1D
0R
1=
1B
0P
0$
b1111110 %
b1111110 +
0#
b10110 *
#225000
1A
1F
0-
1@
1E
b1111110 !
b1111110 ,
0S
1$
#230000
00
05
0D
1N
1R
0.
03
0B
1L
1P
0$
b11011001 %
b11011001 +
1#
b10111 *
#235000
1-
1"
0F
07
02
1S
1O
0E
06
b11011001 !
b11011001 ,
01
1$
#240000
1.
13
0G
10
0:
1D
0I
0R
0$
b10011111 %
b10011111 +
0#
0&
b11000 *
#245000
15
0?
1I
0N
00
12
0<
1F
0K
0-
11
0;
1E
0J
b10110010 !
b10110010 ,
0S
1$
#250000
08
1B
10
0:
1?
1D
0I
1N
1R
0$
b10110111 %
b10110111 +
1&
b11001 *
#255000
1-
17
1S
b10110111 !
b10110111 ,
16
1$
#260000
05
1:
0D
1I
0N
03
18
0B
1G
0L
0$
b1011011 %
b1011011 +
b11010 *
#265000
07
1<
0F
1K
0"
06
1;
0E
1J
b1011011 !
b1011011 ,
0O
1$
#270000
00
0:
1N
0R
0.
08
1L
0P
0$
b11010000 %
b11010000 +
1#
b11011 *
#275000
0-
1"
0<
02
0S
1O
0;
b11010000 !
b11010000 ,
01
1$
#280000
10
15
0I
1.
13
0G
0$
b10010110 %
b10010110 +
b11100 *
#285000
12
17
0K
11
16
b10010110 !
b10010110 ,
0J
1$
#290000
0.
03
18
0=
1G
00
1:
0?
1D
0N
0$
b11001000 %
b11001000 +
0#
0&
b11101 *
#295000
1I
0D
1?
05
0"
1F
0A
1<
02
0O
1E
0@
1;
b101100 !
b101100 ,
01
1$
#300000
10
0:
0I
1.
08
1=
0G
0L
1?
0N
0$
b10010 %
b10010 +
1#
1&
b11110 *
#305000
12
07
0<
1A
0F
11
06
0;
1@
b10010 !
b10010 ,
0E
1$
#310000
0.
18
1B
1P
00
15
0?
1D
1R
0$
b111001 %
b111001 +
0&
b11111 *
#315000
10
1I
0D
1:
05
1-
1F
0A
17
02
1S
1E
0@
16
b100101 !
b100101 ,
01
1$
#320000
15
0:
1N
13
08
0=
0B
1L
00
0?
0D
0I
0$
b10000101 %
b10000101 +
1&
b100000 *
#325000
0F
1"
0E
b10000101 !
b10000101 ,
1O
1$
#330000
03
18
1G
0L
10
05
1:
0N
0$
b1001001 %
b1001001 +
0&
b100001 *
#335000
1?
0:
15
0"
1<
07
12
0O
1;
06
b1011 !
b1011 ,
11
1$
#340000
0R
1=
0P
00
05
1:
1?
1I
0$
b1011000 %
b1011000 +
0#
1&
b100010 *
#345000
02
1A
1K
0-
01
1@
1J
b1011000 !
b1011000 ,
0S
1$
#350000
13
0G
1L
0:
1D
0I
1N
0$
b10011100 %
b10011100 +
0&
b100011 *
#355000
0N
1I
0?
1"
0K
1F
0<
1O
0J
1E
b10110000 !
b10110000 ,
0;
1$
#360000
1.
03
08
1B
1G
0L
1P
0$
b1110011 %
b1110011 +
b100100 *
#365000
0D
1N
0A
1K
0"
0@
1J
b1100000 !
b1100000 ,
0O
1$
#370000
0I
0G
1L
10
1?
1D
1N
1R
0$
b10110011 %
b10110011 +
1#
1&
b100101 *
#375000
1-
1"
0K
1A
12
1S
1O
0J
1@
b10110011 !
b10110011 ,
11
1$
#380000
15
1I
13
1G
0$
b11110111 %
b11110111 +
0#
b100110 *
#385000
17
1K
16
b11110111 !
b11110111 ,
1J
1$
#390000
05
1:
0D
0N
0R
03
18
0B
0L
0P
0$
b1011010 %
b1011010 +
b100111 *
#395000
0-
0"
0F
1<
07
0S
0O
0E
1;
b1011010 !
b1011010 ,
06
1$
#400000
1N
1L
0$
b11011010 %
b11011010 +
1#
b101000 *
#405000
1"
b11011010 !
b11011010 ,
1O
1$
#410000
15
1R
13
1P
0$
b11011111 %
b11011111 +
b101001 *
#415000
1-
17
1S
b11011111 !
b11011111 ,
16
1$
#420000
00
05
0:
0R
0.
03
08
0P
0$
b11010000 %
b11010000 +
0#
b101010 *
#425000
02
07
0<
0-
01
06
0;
b11010000 !
b11010000 ,
0S
1$
#430000
1.
13
18
0=
0G
0L
0?
1D
0I
1R
0$
b1110 %
b1110 +
1#
0&
b101011 *
#435000
10
0N
1I
0D
1-
0K
1F
0A
1S
0J
1E
b10100001 !
b10100001 ,
0@
1$
#440000
0.
1=
1B
1G
1L
1P
0R
0$
b11111101 %
b11111101 +
0#
b101100 *
#445000
15
0I
1N
00
12
0F
1K
0"
0-
11
0E
1J
0O
b1000010 !
b1000010 ,
0S
1$
#450000
10
0N
1.
0=
0B
0L
0P
1:
0?
0D
1I
0R
0$
b1001110 %
b1001110 +
1&
b101101 *
#455000
1<
17
1;
b1001110 !
b1001110 ,
16
1$
#460000
0:
1?
1D
0I
1N
08
1=
1B
0G
1L
0$
b10110110 %
b10110110 +
b101110 *
#465000
0<
1A
1F
0K
1"
0;
1@
1E
0J
b10110110 !
b10110110 ,
1O
1$
#470000
0.
03
18
00
1:
0?
1I
0N
1R
0$
b10111000 %
b10111000 +
1#
0&
b101111 *
#475000
10
1N
0D
1?
05
1-
0"
1K
0A
1<
02
1S
0O
1J
0@
1;
b1101101 !
b1101101 ,
01
1$
#480000
13
08
0=
0B
0L
0$
b100 %
b100 +
b110000 *
#485000
15
0:
1D
0I
12
07
1A
0F
1"
11
06
1@
0E
b11011011 !
b11011011 ,
1O
1$
#490000
1:
1I
18
1G
1P
00
0?
0D
0N
1R
0$
b1001101 %
b1001101 +
1&
b110001 *
#495000
0"
0A
17
02
0O
0@
16
b1001101 !
b1001101 ,
01
1$
#500000
0$
b110010 *
