projects/verilog_tutorials/project_0/04_shift_register/shift_register.v
module shift_register
#(
	parameter bit_size = 8
)
(
	input 				  clk,
	input 				  load,
	input 				  Sin,
	input  [bit_size-1:0] d,
	output [bit_size-1:0] q
);

	mux_dff
	u_mux_dff(
		.clk				(clk				),
		.load				(load				),
		.in0				(Sin				),
		.in1				(d[0]				),
		.q					(q[0]				)
	);

	genvar i;
	generate
		for (i=1; i<bit_size; i=i+1) begin : shift_register_block
			mux_dff
			u_mux_dff(
				.clk				(clk				),
				.load				(load				),
				.in0				(q[i-1]				),
				.in1				(d[i]				),
				.q					(q[i]				)
			);
		end
	endgenerate
	
endmodule

module mux_dff
(
	input clk,
	input load,
	input in0,
	input in1,
	output reg q
);

	reg mux_out;

	always @ (*) begin
		case(load)
			0 : mux_out = in0;
			1 : mux_out = in1;
		endcase
	end

	always @ (posedge clk) begin
		q <= mux_out;
	end
endmodule

projects/verilog_tutorials/project_0/04_shift_register/shift_register_tb.v
// --------------------------------------------------
//	Define Global Variables
// --------------------------------------------------
`define	CLKFREQ		100		// Clock Freq. (Unit: MHz)
`define	SIMCYCLE	`NVEC	// Sim. Cycles
`define NVEC		10		// # of Test Vector

// --------------------------------------------------
//	Includes
// --------------------------------------------------
`include	"shift_register.v"

module shift_register_tb;
// --------------------------------------------------
//	DUT Signals & Instantiate
// --------------------------------------------------
	parameter bit_size = 8;

	reg 				  clk;
	reg 				  load;
	reg 				  Sin;
	reg  [bit_size-1:0] d;
	wire [bit_size-1:0] q;

	shift_register
	#(
		.bit_size			(bit_size			)
	)
	u_shift_register(
		.clk				(clk				),
		.load				(load				),
		.Sin				(Sin				),
		.d					(d					),
		.q					(q					)
	);

// --------------------------------------------------
//	Tasks
// --------------------------------------------------
	task init;
		begin
			clk = 0;
			load = 0;
			Sin = 0;
			d = 0;
		end
	endtask

// --------------------------------------------------
//	clock 
// --------------------------------------------------
	always #(500/`CLKFREQ) clk = ~clk;

// --------------------------------------------------
//	Test Stimulus
// --------------------------------------------------
	integer		i, j;
	initial begin
		init();

		for (i=0; i<`SIMCYCLE; i++) begin
			load = 0;
			Sin  = $urandom;
			d	 = $urandom;
			#(1000/`CLKFREQ);
		end
		$finish;
	end

// --------------------------------------------------
//	Dump VCD
// --------------------------------------------------
	reg	[8*32-1:0]	vcd_file;
	initial begin
		if ($value$plusargs("vcd_file=%s", vcd_file)) begin
			$dumpfile(vcd_file);
			$dumpvars;
		end else begin
			$dumpfile("shift_register_tb.vcd");
			$dumpvars;
		end
	end

endmodule

projects/verilog_tutorials/project_0/04_shift_register/vcd/shift_register.vcd
$date
	Tue Jul  2 17:45:57 2024
$end
$version
	Icarus Verilog
$end
$timescale
	1ps
$end
$scope module shift_register_tb $end
$var wire 8 ! q [7:0] $end
$var reg 1 " Sin $end
$var reg 1 # clk $end
$var reg 8 $ d [7:0] $end
$var reg 1 % load $end
$var reg 256 & vcd_file [255:0] $end
$var integer 32 ' i [31:0] $end
$scope module u_shift_register $end
$var wire 1 " Sin $end
$var wire 1 # clk $end
$var wire 8 ( d [7:0] $end
$var wire 1 % load $end
$var wire 8 ) q [7:0] $end
$scope begin shift_register_block[1] $end
$scope module u_mux_dff $end
$var wire 1 # clk $end
$var wire 1 * in0 $end
$var wire 1 + in1 $end
$var wire 1 % load $end
$var reg 1 , mux_out $end
$var reg 1 - q $end
$upscope $end
$upscope $end
$scope begin shift_register_block[2] $end
$scope module u_mux_dff $end
$var wire 1 # clk $end
$var wire 1 . in0 $end
$var wire 1 / in1 $end
$var wire 1 % load $end
$var reg 1 0 mux_out $end
$var reg 1 1 q $end
$upscope $end
$upscope $end
$scope begin shift_register_block[3] $end
$scope module u_mux_dff $end
$var wire 1 # clk $end
$var wire 1 2 in0 $end
$var wire 1 3 in1 $end
$var wire 1 % load $end
$var reg 1 4 mux_out $end
$var reg 1 5 q $end
$upscope $end
$upscope $end
$scope begin shift_register_block[4] $end
$scope module u_mux_dff $end
$var wire 1 # clk $end
$var wire 1 6 in0 $end
$var wire 1 7 in1 $end
$var wire 1 % load $end
$var reg 1 8 mux_out $end
$var reg 1 9 q $end
$upscope $end
$upscope $end
$scope begin shift_register_block[5] $end
$scope module u_mux_dff $end
$var wire 1 # clk $end
$var wire 1 : in0 $end
$var wire 1 ; in1 $end
$var wire 1 % load $end
$var reg 1 < mux_out $end
$var reg 1 = q $end
$upscope $end
$upscope $end
$scope begin shift_register_block[6] $end
$scope module u_mux_dff $end
$var wire 1 # clk $end
$var wire 1 > in0 $end
$var wire 1 ? in1 $end
$var wire 1 % load $end
$var reg 1 @ mux_out $end
$var reg 1 A q $end
$upscope $end
$upscope $end
$scope begin shift_register_block[7] $end
$scope module u_mux_dff $end
$var wire 1 # clk $end
$var wire 1 B in0 $end
$var wire 1 C in1 $end
$var wire 1 % load $end
$var reg 1 D mux_out $end
$var reg 1 E q $end
$upscope $end
$upscope $end
$scope module u_mux_dff $end
$var wire 1 # clk $end
$var wire 1 " in0 $end
$var wire 1 F in1 $end
$var wire 1 % load $end
$var reg 1 G mux_out $end
$var reg 1 H q $end
$upscope $end
$upscope $end
$scope task init $end
$upscope $end
$upscope $end
$enddefinitions $end
#0
$dumpvars
xH
0G
1F
xE
xD
1C
xB
xA
x@
0?
x>
x=
x<
0;
x:
x9
x8
07
x6
x5
x4
03
x2
x1
x0
0/
x.
x-
x,
0+
x*
bx )
b10000001 (
b0 '
b1011100010111101110110011000110110010000101111011100110110100001101001011001100111010001011111011100100110010101100111011010010111001101110100011001010111001000101110011101100110001101100100 &
0%
b10000001 $
0#
0"
bx !
$end
#5000
0,
0*
bx0 !
bx0 )
0H
1#
#10000
1+
1;
1?
0C
1G
0#
b1100011 $
b1100011 (
1"
b1 '
#15000
1,
00
1*
0.
1H
bx01 !
bx01 )
0-
1#
#20000
0+
1/
13
0;
0?
1C
0#
b10001101 $
b10001101 (
b10 '
#25000
10
04
1.
02
1-
bx011 !
bx011 )
01
1#
#30000
1+
0/
03
17
0C
0F
0#
b10010 $
b10010 (
b11 '
#35000
08
14
06
12
05
bx0111 !
bx0111 )
11
1#
#40000
0+
1/
13
07
1F
0#
b1101 $
b1101 (
b100 '
#45000
18
0<
16
0:
15
bx01111 !
bx01111 )
09
1#
#50000
17
1;
0G
0#
b111101 $
b111101 (
0"
b101 '
#55000
0,
0@
1<
0*
0>
1:
0H
0=
bx011110 !
bx011110 )
19
1#
#60000
07
0;
1C
0F
1G
0#
b10001100 $
b10001100 (
1"
b110 '
#65000
00
1@
0D
1,
0.
1>
0B
1*
0-
1=
0A
bx0111101 !
bx0111101 )
1H
1#
#70000
1+
03
1?
0#
b11000110 $
b11000110 (
b111 '
#75000
1D
04
10
1B
02
1.
0E
1A
01
b1111011 !
b1111011 )
1-
1#
#80000
0/
13
1;
0?
0#
b10101010 $
b10101010 (
b1000 '
#85000
14
08
12
06
11
05
b11110111 !
b11110111 )
1E
1#
#90000
1/
03
17
1?
0C
1F
0#
b1110111 $
b1110111 (
b1001 '
#95000
0<
18
0:
16
09
b11101111 !
b11101111 )
15
1#
#100000
0#
b1010 '
