projects/verilog_tutorials/project_0/04_shift_register/shift_register.v
module shift_register
#(
	parameter bit_size = 8
)
(
	input clk,
	input load,
	input Sin,
	input [bit_size-1:0] d,
	output [bit_size-1:0] q
);
	
	genvar i;
	generate
		for (i=0; i<bit_size; i=i+1) begin : shift_register_block
			mux_dff
			u_mux_dff(
				.clk				(clk				),
				.load				(load				),
				.Sin				(Sin				),
				.d					(d[i]				),
				.q					(q[i]				)
			);
		end
	endgenerate
	
endmodule

module mux_dff
(
	input clk,
	input load,
	input Sin,
	input d,
	output reg q,
	output reg Sout
);

	reg mux_out;

	always @ (*) begin
		case(load)
			0 : mux_out = Sin;
			1 : mux_out = d;
		endcase
	end

	always @ (posedge clk) begin
		q <= mux_out;
	end

endmodule

projects/verilog_tutorials/project_0/04_shift_register/shift_register_tb.v
// --------------------------------------------------
//	Define Global Variables
// --------------------------------------------------
`define	CLKFREQ		100		// Clock Freq. (Unit: MHz)
`define	SIMCYCLE	`NVEC	// Sim. Cycles
`define NVEC		50		// # of Test Vector

// --------------------------------------------------
//	Includes
// --------------------------------------------------
`include	"shift_register.v"

module shift_register_tb;
// --------------------------------------------------
//	DUT Signals & Instantiate
// --------------------------------------------------
	reg clk;
	reg load;
	reg Sin;
	reg [bit_size-1:0] d;
	wire [bit_size-1:0] q;

	parameter bit_size = 8;

	shift_register
	#(
		.bit_size			(bit_size			)
	)
	u_shift_register(
		.clk				(clk				),
		.load				(load				),
		.Sin				(Sin				),
		.d					(d					),
		.q					(q					)
	);




// --------------------------------------------------
//	Tasks
// --------------------------------------------------
	reg [8*32-1:0] taskState;
	integer err = 0;

	task init;
		begin
			taskState = "Init";
			clk = 0;
			load = 0;
			Sin = 0;
			d= 0;
		end
	endtask

	always #(500/`CLKFREQ) clk = ~clk;

// --------------------------------------------------
//	Test Stimulus
// --------------------------------------------------
	integer		i, j;
	initial begin
		init();

		for (i=0; i<`SIMCYCLE; i++) begin
			load = $urandom;
			Sin = $urandom;
			d	= $urandom;
			#(1000/`CLKFREQ);
		end
		$finish;
	end

// --------------------------------------------------
//	Dump VCD
// --------------------------------------------------
	reg	[8*32-1:0]	vcd_file;
	initial begin
		if ($value$plusargs("vcd_file=%s", vcd_file)) begin
			$dumpfile(vcd_file);
			$dumpvars;
		end else begin
			$dumpfile("shift_register_tb.vcd");
			$dumpvars;
		end
	end

endmodule

projects/verilog_tutorials/project_0/04_shift_register/vcd/shift_register.vcd
$date
	Fri Jun 28 18:27:51 2024
$end
$version
	Icarus Verilog
$end
$timescale
	1ps
$end
$scope module shift_register_tb $end
$var wire 8 ! q [7:0] $end
$var reg 1 " Sin $end
$var reg 1 # clk $end
$var reg 8 $ d [7:0] $end
$var reg 1 % load $end
$var reg 256 & taskState [255:0] $end
$var reg 256 ' vcd_file [255:0] $end
$var integer 32 ( err [31:0] $end
$var integer 32 ) i [31:0] $end
$scope module u_shift_register $end
$var wire 1 " Sin $end
$var wire 1 # clk $end
$var wire 8 * d [7:0] $end
$var wire 1 % load $end
$var wire 8 + q [7:0] $end
$scope begin shift_register_block[0] $end
$scope module u_mux_dff $end
$var wire 1 " Sin $end
$var wire 1 # clk $end
$var wire 1 , d $end
$var wire 1 % load $end
$var reg 1 - Sout $end
$var reg 1 . mux_out $end
$var reg 1 / q $end
$upscope $end
$upscope $end
$scope begin shift_register_block[1] $end
$scope module u_mux_dff $end
$var wire 1 " Sin $end
$var wire 1 # clk $end
$var wire 1 0 d $end
$var wire 1 % load $end
$var reg 1 1 Sout $end
$var reg 1 2 mux_out $end
$var reg 1 3 q $end
$upscope $end
$upscope $end
$scope begin shift_register_block[2] $end
$scope module u_mux_dff $end
$var wire 1 " Sin $end
$var wire 1 # clk $end
$var wire 1 4 d $end
$var wire 1 % load $end
$var reg 1 5 Sout $end
$var reg 1 6 mux_out $end
$var reg 1 7 q $end
$upscope $end
$upscope $end
$scope begin shift_register_block[3] $end
$scope module u_mux_dff $end
$var wire 1 " Sin $end
$var wire 1 # clk $end
$var wire 1 8 d $end
$var wire 1 % load $end
$var reg 1 9 Sout $end
$var reg 1 : mux_out $end
$var reg 1 ; q $end
$upscope $end
$upscope $end
$scope begin shift_register_block[4] $end
$scope module u_mux_dff $end
$var wire 1 " Sin $end
$var wire 1 # clk $end
$var wire 1 < d $end
$var wire 1 % load $end
$var reg 1 = Sout $end
$var reg 1 > mux_out $end
$var reg 1 ? q $end
$upscope $end
$upscope $end
$scope begin shift_register_block[5] $end
$scope module u_mux_dff $end
$var wire 1 " Sin $end
$var wire 1 # clk $end
$var wire 1 @ d $end
$var wire 1 % load $end
$var reg 1 A Sout $end
$var reg 1 B mux_out $end
$var reg 1 C q $end
$upscope $end
$upscope $end
$scope begin shift_register_block[6] $end
$scope module u_mux_dff $end
$var wire 1 " Sin $end
$var wire 1 # clk $end
$var wire 1 D d $end
$var wire 1 % load $end
$var reg 1 E Sout $end
$var reg 1 F mux_out $end
$var reg 1 G q $end
$upscope $end
$upscope $end
$scope begin shift_register_block[7] $end
$scope module u_mux_dff $end
$var wire 1 " Sin $end
$var wire 1 # clk $end
$var wire 1 H d $end
$var wire 1 % load $end
$var reg 1 I Sout $end
$var reg 1 J mux_out $end
$var reg 1 K q $end
$upscope $end
$upscope $end
$upscope $end
$scope task init $end
$upscope $end
$upscope $end
$enddefinitions $end
#0
$dumpvars
xK
1J
xI
0H
xG
1F
xE
0D
xC
1B
xA
0@
x?
1>
x=
0<
x;
1:
x9
18
x7
16
x5
04
x3
12
x1
00
x/
1.
x-
1,
bx +
b1001 *
b0 )
b0 (
b1011100010111101110110011000110110010000101111011100110110100001101001011001100111010001011111011100100110010101100111011010010111001101110100011001010111001000101110011101100110001101100100 '
b1001001011011100110100101110100 &
0%
b1001 $
0#
1"
bx !
$end
#5000
1/
13
17
1;
1?
1C
1G
b11111111 !
b11111111 +
1K
1#
#10000
14
1H
02
16
0>
0B
0F
1J
0#
b10001101 $
b10001101 *
1%
b1 )
#15000
0G
0C
0?
b10001101 !
b10001101 +
03
1#
#20000
06
0:
0J
04
08
0H
0#
b1 $
b1 *
0"
b10 )
#25000
07
0;
b1 !
b1 +
0K
1#
#30000
16
1:
1>
1B
14
18
1<
1@
0#
b111101 $
b111101 *
b11 )
#35000
1C
1?
1;
b111101 !
b111101 +
17
1#
#40000
06
1F
1J
04
1D
1H
0#
b11111001 $
b11111001 *
b100 )
#45000
07
1G
b11111001 !
b11111001 +
1K
1#
#50000
0,
10
0<
0D
12
16
0#
b10101010 $
b10101010 *
1"
0%
b101 )
#55000
17
b11111111 !
b11111111 +
13
1#
#60000
0:
0B
0J
08
1<
0@
0H
0.
06
1>
0F
0#
b10010 $
b10010 *
1%
b110 )
#65000
0/
07
0;
0C
0G
b10010 !
b10010 +
0K
1#
#70000
16
1:
0>
1F
1J
14
18
0<
1D
1H
0#
b11001110 $
b11001110 *
0"
b111 )
#75000
1K
1G
0?
1;
b11001110 !
b11001110 +
17
1#
#80000
00
1<
0H
1.
1>
1B
0#
b1011100 $
b1011100 *
1"
0%
b1000 )
#85000
1/
1?
b11111111 !
b11111111 +
1C
1#
#90000
0:
0>
1,
08
0<
1@
1.
02
1B
0J
0#
b1100101 $
b1100101 *
1%
b1001 )
#95000
0K
0?
0;
b1100101 !
b1100101 +
03
1#
#100000
0.
06
0B
0F
1J
0,
04
0@
0D
1H
0#
b10000000 $
b10000000 *
0"
b1010 )
#105000
0/
07
0C
0G
b10000000 !
b10000000 +
1K
1#
#110000
1,
14
18
1<
0J
0#
b10011101 $
b10011101 *
0%
b1011 )
#115000
b0 !
b0 +
0K
1#
#120000
0<
0H
1.
12
16
1:
1>
1B
1F
1J
0#
b1101 $
b1101 *
1"
b1100 )
#125000
1/
13
17
1;
1?
1C
1G
b11111111 !
b11111111 +
1K
1#
#130000
0:
08
1<
1D
1H
02
1>
0B
1F
1J
0#
b11010101 $
b11010101 *
1%
b1101 )
#135000
0C
0;
b11010101 !
b11010101 +
03
1#
#140000
18
0D
0H
0.
06
0>
0F
0J
0#
b11101 $
b11101 *
0"
0%
b1110 )
#145000
0/
07
0?
0G
b0 !
b0 +
0K
1#
#150000
12
0,
10
04
0<
0.
06
1:
0>
0#
b1010 $
b1010 *
1"
1%
b1111 )
#155000
1;
b1010 !
b1010 +
13
1#
#160000
08
1<
1@
1D
1H
02
0:
0#
b11110010 $
b11110010 *
0"
0%
b10000 )
#165000
03
b0 !
b0 +
0;
1#
#170000
00
18
0@
1.
12
16
1:
1>
1B
1F
1J
0#
b11011000 $
b11011000 *
1"
b10001 )
#175000
1K
1G
1C
1?
1;
17
13
b11111111 !
b11111111 +
1/
1#
#180000
1,
10
0<
1@
0#
b11101011 $
b11101011 *
b10010 )
#185000
1#
#190000
0,
14
0D
0.
02
06
0:
0>
0B
0F
0J
0#
b10101110 $
b10101110 *
0"
b10011 )
#195000
0K
0G
0C
0?
0;
07
03
b0 !
b0 +
0/
1#
#200000
1,
04
0@
0H
0#
b1011 $
b1011 *
b10100 )
#205000
1#
#210000
16
1F
14
1D
1.
12
1:
0#
b1001111 $
b1001111 *
1"
1%
b10101 )
#215000
1G
1;
17
13
b1001111 !
b1001111 +
1/
1#
#220000
0.
1>
1B
0,
1<
1@
0#
b1111110 $
b1111110 *
0"
b10110 )
#225000
0/
1?
b1111110 !
b1111110 +
1C
1#
#230000
1.
02
06
0B
1J
1,
00
04
0@
1H
0#
b11011001 $
b11011001 *
1"
b10111 )
#235000
1K
0C
07
03
b11011001 !
b11011001 +
1/
1#
#240000
10
14
0D
0.
0:
0>
0F
0J
0#
b10011111 $
b10011111 *
0"
0%
b11000 )
#245000
0/
0;
0?
0G
b0 !
b0 +
0K
1#
#250000
1B
08
1@
1.
12
16
0:
1>
1J
0#
b10110111 $
b10110111 *
1%
b11001 )
#255000
1K
1C
1?
17
13
b10110111 !
b10110111 +
1/
1#
#260000
06
1:
0B
1F
0J
04
18
0@
1D
0H
0#
b1011011 $
b1011011 *
b11010 )
#265000
07
1;
0C
1G
b1011011 !
b1011011 +
0K
1#
#270000
0.
02
0:
1J
0,
00
08
1H
0#
b11010000 $
b11010000 *
1"
b11011 )
#275000
1K
0;
03
b11010000 !
b11010000 +
0/
1#
#280000
12
16
0F
10
14
0D
0#
b10010110 $
b10010110 *
b11100 )
#285000
13
17
b10010110 !
b10010110 +
0G
1#
#290000
00
04
18
0<
1D
02
06
0>
0J
0#
b11001000 $
b11001000 *
0"
0%
b11101 )
#295000
0K
0?
07
b0 !
b0 +
03
1#
#300000
12
1>
10
08
1<
0D
0H
0:
0F
0J
0#
b10010 $
b10010 *
1"
1%
b11110 )
#305000
13
b10010 !
b10010 +
1?
1#
#310000
1,
00
18
1@
1.
16
1:
1B
1F
1J
0#
b111001 $
b111001 *
0%
b11111 )
#315000
1K
1G
1C
1;
17
b11111111 !
b11111111 +
1/
1#
#320000
0:
0>
0B
14
08
0<
0@
1H
02
16
0F
1J
0#
b10000101 $
b10000101 *
1%
b100000 )
#325000
03
0;
0?
0C
b10000101 !
b10000101 +
0G
1#
#330000
04
18
1D
0H
12
1:
1>
1B
1F
0#
b1001001 $
b1001001 *
0%
b100001 )
#335000
1G
1C
1?
1;
b11111111 !
b11111111 +
13
1#
#340000
0.
0,
1<
02
06
1>
0B
0J
0#
b1011000 $
b1011000 *
0"
1%
b100010 )
#345000
0/
03
07
0C
b1011000 !
b1011000 +
0K
1#
#350000
14
0D
1H
0:
0>
0F
0#
b10011100 $
b10011100 *
0%
b100011 )
#355000
0G
0?
b0 !
b0 +
0;
1#
#360000
1,
10
04
08
1@
1D
0H
0#
b1110011 $
b1110011 *
b100100 )
#365000
1#
#370000
1J
0D
1H
1.
12
1>
1B
0F
0#
b10110011 $
b10110011 *
1"
1%
b100101 )
#375000
1K
1C
1?
13
b10110011 !
b10110011 +
1/
1#
#380000
16
1F
14
1D
0#
b11110111 $
b11110111 *
0"
b100110 )
#385000
17
b11110111 !
b11110111 +
1G
1#
#390000
0.
06
1:
0B
0J
0,
04
18
0@
0H
0#
b1011010 $
b1011010 *
b100111 )
#395000
0K
0C
1;
07
b1011010 !
b1011010 +
0/
1#
#400000
1J
1H
0#
b11011010 $
b11011010 *
1"
b101000 )
#405000
b11011010 !
b11011010 +
1K
1#
#410000
1.
16
1,
14
0#
b11011111 $
b11011111 *
b101001 )
#415000
17
b11011111 !
b11011111 +
1/
1#
#420000
0.
02
06
0:
0,
00
04
08
0#
b11010000 $
b11010000 *
0"
b101010 )
#425000
0/
03
07
b11010000 !
b11010000 +
0;
1#
#430000
10
14
18
0<
0D
0H
1.
12
16
1:
1B
0#
b1110 $
b1110 *
1"
0%
b101011 )
#435000
1C
1;
17
13
b11111111 !
b11111111 +
1/
1#
#440000
1,
00
1<
1@
1D
1H
0.
02
06
0:
0>
0B
0F
0J
0#
b11111101 $
b11111101 *
0"
b101100 )
#445000
0/
03
07
0;
0?
0C
0G
b0 !
b0 +
0K
1#
#450000
12
0,
10
0<
0@
0H
0.
16
1:
0>
0B
1F
0J
0#
b1001110 $
b1001110 *
1%
b101101 )
#455000
1G
1;
17
b1001110 !
b1001110 +
13
1#
#460000
0:
1>
1B
0F
1J
08
1<
1@
0D
1H
0#
b10110110 $
b10110110 *
b101110 )
#465000
0;
1?
1C
0G
b10110110 !
b10110110 +
1K
1#
#470000
00
04
18
1.
1:
1F
0#
b10111000 $
b10111000 *
1"
0%
b101111 )
#475000
1G
1;
b11111111 !
b11111111 +
1/
1#
#480000
14
08
0<
0@
0H
0#
b100 $
b100 *
b110000 )
#485000
1#
#490000
1,
18
1D
1.
02
1:
0>
0B
1F
0J
0#
b1001101 $
b1001101 *
1%
b110001 )
#495000
0K
0C
0?
b1001101 !
b1001101 +
03
1#
#500000
0#
b110010 )
