projects/verilog_tutorials/project_0/05_fsm_traffic_light/fsm_traffic.v
// ==================================================
//	[ VLSISYS Lab. ]
//	* Author		: HyeRyun Lim (imh2880@gmail.com)
//	* Filename		: fsm_traffic.v
//	* Date			: 2024-06-28 16:32:43
//	* Description	: 
// ==================================================
module fsm_traffic
(
	input clk,
	input rstn,
	input Ta,
	input Tb,
	input P,
	input R,
	output reg  [1:0] La,
	output reg	[1:0] Lb
);

	localparam S0 = 0;
	localparam S1 = 1;
	localparam S2 = 2;
	localparam S3 = 3;
	localparam SP0 = 0;
	localparam SP1 = 1;
	
	parameter green = 0, yellow = 1, red = 2;

	wire M;
	reg [1:0] state, next_state;
	reg p_state, p_next_state;

	always @ (*) begin
		case(p_state)
			SP0 : p_next_state = P ? SP1 : SP0;
			SP1 : p_next_state = R ? SP0 : SP1;
		endcase
	end

	assign M = (p_state == SP1);
	always @ (*) begin
		case(state)
			S0 : next_state = Ta ? S0 : S1;
			S1 : next_state = S2;
			S2 : next_state = (M | Tb) ? S2 : S3;
			S3 : next_state = S0;
		endcase
	end

	always @ (posedge clk) begin
		if(!rstn) begin
			state <= S0;
			p_state <= SP0;
		end
		else begin
			state <= next_state;
			p_state <= p_next_state;
		end
	end

	always @ (*) begin
		case(state)
			S0 : begin
				La = green;
				Lb = red;
			end
			S1 : begin
				La = yellow;
				Lb = red;
			end
			S2 : begin
				La = red;
				Lb = green;
			end
			S3 : begin
				La = red;
				Lb = yellow;
			end
		endcase
	end

	`ifdef	DEBUG
			reg [8*32-1:0] light_stateMonitor;
			reg [8*32-1:0] parade_stateMonitor;
			reg [8*32-1:0] out_La_stateMonitor;
			reg [8*32-1:0] out_Lb_stateMonitor;
			always @ (*) begin
				case(state)
					S0 : light_stateMonitor = "S0";
					S1 : light_stateMonitor = "S1";
					S2 : light_stateMonitor = "S2";
					S3 : light_stateMonitor = "S3";
				endcase

				case(p_state)
					S0 : parade_stateMonitor = "SP0";
					S1 : parade_stateMonitor = "SP1";
				endcase

				case(La)
					green : out_La_stateMonitor = "green";
					yellow : out_La_stateMonitor = "yellow";
					red : out_La_stateMonitor = "red";
				endcase

				case(Lb)
					green : out_Lb_stateMonitor = "green";
					yellow : out_Lb_stateMonitor = "yellow";
					red : out_Lb_stateMonitor = "red";
				endcase
			end
		`endif
endmodule

projects/verilog_tutorials/project_0/05_fsm_traffic_light/fsm_traffic_tb.v
// // --------------------------------------------------
//	Define Global Variables
// --------------------------------------------------
`define	CLKFREQ		100		// Clock Freq. (Unit: MHz)
`define	SIMCYCLE	`NVEC	// Sim. Cycles
`define NVEC		50		// # of Test Vector
`define DEBUG

// --------------------------------------------------
//	Includes
// --------------------------------------------------
`include	"fsm_traffic.v"

module fsm_traffic_tb;
// --------------------------------------------------
//	DUT Signals & Instantiate
// --------------------------------------------------
	reg clk;
	reg rstn;
	reg Ta;
	reg Tb;
	reg P;
	reg R;
	wire [1:0] La;
	wire [1:0] Lb;

	fsm_traffic
	u_fsm_traffic(
		.clk				(clk				),
		.rstn				(rstn				),
		.Ta					(Ta					),
		.Tb					(Tb					),
		.P					(P					),
		.R					(R					),
		.La					(La					),
		.Lb					(Lb					)
	);


// --------------------------------------------------
//	Tasks
// --------------------------------------------------
	reg [8*32-1:0] taskState;
	integer err = 0;

	task init;
		begin
			taskState = "Init";
			clk = 0;
			rstn = 0;
			P = 0;
			R = 0;
			Ta = 0;
			Tb = 0;
		end
	endtask

	task resetReleaseAfterNCycles;
		input [9:0] n;
		begin
			taskState = "Reset On";
			rstn = 1'b0;
			#(1000/`CLKFREQ);
			rstn = 1'b1; 
			taskState = "Reset OFF";
		end
	endtask

	always #(500/`CLKFREQ) clk = ~clk;

// --------------------------------------------------
//	Test Stimulus
// --------------------------------------------------
	integer		i, j;
	initial begin
		init();
		resetReleaseAfterNCycles(4);

		for (i=0; i<`SIMCYCLE; i++) begin
			P = $urandom;
			R = $urandom;
			Ta = $urandom;
			Tb = $urandom;
			#(1000/`CLKFREQ);
		end
		$finish;
	end

// --------------------------------------------------
//	Dump VCD
// --------------------------------------------------
	reg	[8*32-1:0]	vcd_file;
	initial begin
		if ($value$plusargs("vcd_file=%s", vcd_file)) begin
			$dumpfile(vcd_file);
			$dumpvars;
		end else begin
			$dumpfile("fsm_traffic_tb.vcd");
			$dumpvars;
		end
	end

endmodule

projects/verilog_tutorials/project_0/05_fsm_traffic_light/vcd/fsm_traffic.vcd
$date
	Tue Jul  2 16:14:17 2024
$end
$version
	Icarus Verilog
$end
$timescale
	1ps
$end
$scope module fsm_traffic_tb $end
$var wire 2 ! Lb [1:0] $end
$var wire 2 " La [1:0] $end
$var reg 1 # P $end
$var reg 1 $ R $end
$var reg 1 % Ta $end
$var reg 1 & Tb $end
$var reg 1 ' clk $end
$var reg 1 ( rstn $end
$var reg 256 ) taskState [255:0] $end
$var reg 256 * vcd_file [255:0] $end
$var integer 32 + err [31:0] $end
$var integer 32 , i [31:0] $end
$scope module u_fsm_traffic $end
$var wire 1 # P $end
$var wire 1 $ R $end
$var wire 1 % Ta $end
$var wire 1 & Tb $end
$var wire 1 ' clk $end
$var wire 1 ( rstn $end
$var wire 1 - M $end
$var reg 2 . La [1:0] $end
$var reg 2 / Lb [1:0] $end
$var reg 256 0 light_stateMonitor [255:0] $end
$var reg 2 1 next_state [1:0] $end
$var reg 256 2 out_La_stateMonitor [255:0] $end
$var reg 256 3 out_Lb_stateMonitor [255:0] $end
$var reg 1 4 p_next_state $end
$var reg 1 5 p_state $end
$var reg 256 6 parade_stateMonitor [255:0] $end
$var reg 2 7 state [1:0] $end
$upscope $end
$scope task init $end
$upscope $end
$scope task resetReleaseAfterNCycles $end
$var reg 10 8 n [9:0] $end
$upscope $end
$upscope $end
$enddefinitions $end
#0
$dumpvars
b100 8
bx 7
bx 6
x5
x4
bx 3
bx 2
bx 1
bx 0
bx /
bx .
x-
bx ,
b0 +
b1011100010111101110110011000110110010000101111011001100111001101101101010111110111010001110010011000010110011001100110011010010110001100101110011101100110001101100100 *
b101001001100101011100110110010101110100001000000100111101101110 )
0(
0'
0&
0%
0$
0#
bx "
bx !
$end
#5000
04
b11100100110010101100100 3
b110011101110010011001010110010101101110 2
b10100110101000000110000 6
b101001100110000 0
b10 !
b10 /
b0 "
b0 .
b1 1
0-
05
b0 7
1'
#10000
b0 1
0'
1&
1%
1$
b0 ,
b10100100110010101110011011001010111010000100000010011110100011001000110 )
1(
#15000
1'
#20000
14
0'
0&
1#
b1 ,
#25000
b10100110101000000110001 6
04
1-
15
1'
#30000
b1 1
0'
1&
0%
b10 ,
#35000
14
b11110010110010101101100011011000110111101110111 2
b10100110101000000110000 6
b101001100110001 0
b1 "
b1 .
b10 1
0-
05
b1 7
1'
#40000
0'
0&
1%
0$
b11 ,
#45000
b110011101110010011001010110010101101110 3
b11100100110010101100100 2
b10100110101000000110001 6
b101001100110010 0
b0 !
b0 /
b10 "
b10 .
1-
15
b10 7
1'
#50000
0'
1&
b100 ,
#55000
1'
#60000
04
0'
0&
0%
1$
0#
b101 ,
#65000
b10100110101000000110000 6
b11 1
0-
05
1'
#70000
b10 1
0'
1&
b110 ,
#75000
1'
#80000
b11 1
14
0'
0&
1%
1#
b111 ,
#85000
04
b11110010110010101101100011011000110111101110111 3
b10100110101000000110001 6
b101001100110011 0
b1 !
b1 /
b0 1
1-
15
b11 7
1'
#90000
14
0'
1&
0%
0$
0#
b1000 ,
#95000
b11100100110010101100100 3
b110011101110010011001010110010101101110 2
b101001100110000 0
b10 !
b10 /
b0 "
b0 .
b1 1
b0 7
1'
#100000
b0 1
04
0'
1%
1$
b1001 ,
#105000
b10100110101000000110000 6
0-
05
1'
#110000
b1 1
14
0'
0&
0%
1#
b1010 ,
#115000
04
b11110010110010101101100011011000110111101110111 2
b10100110101000000110001 6
b101001100110001 0
b1 "
b1 .
b10 1
1-
15
b1 7
1'
#120000
0'
1%
b1011 ,
#125000
14
b110011101110010011001010110010101101110 3
b11100100110010101100100 2
b10100110101000000110000 6
b101001100110010 0
b0 !
b0 /
b10 "
b10 .
b11 1
0-
05
b10 7
1'
#130000
04
0'
0%
0$
0#
b1100 ,
#135000
b11110010110010101101100011011000110111101110111 3
b101001100110011 0
b1 !
b1 /
b0 1
b11 7
1'
#140000
14
0'
1&
1#
b1101 ,
#145000
b11100100110010101100100 3
b110011101110010011001010110010101101110 2
b10100110101000000110001 6
b101001100110000 0
b10 !
b10 /
b0 "
b0 .
b1 1
1-
15
b0 7
1'
#150000
0'
0&
b1110 ,
#155000
b11110010110010101101100011011000110111101110111 2
b101001100110001 0
b1 "
b1 .
b10 1
b1 7
1'
#160000
0'
1&
1%
0#
b1111 ,
#165000
b110011101110010011001010110010101101110 3
b11100100110010101100100 2
b101001100110010 0
b0 !
b0 /
b10 "
b10 .
b10 7
1'
#170000
04
0'
0&
1$
1#
b10000 ,
#175000
b10100110101000000110000 6
14
b11 1
0-
05
1'
#180000
b10 1
04
0'
1&
0#
b10001 ,
#185000
1'
#190000
0'
0$
b10010 ,
#195000
1'
#200000
b11 1
0'
0&
1$
b10011 ,
#205000
b11110010110010101101100011011000110111101110111 3
b101001100110011 0
b1 !
b1 /
b0 1
b11 7
1'
#210000
14
0'
1#
b10100 ,
#215000
04
b11100100110010101100100 3
b110011101110010011001010110010101101110 2
b10100110101000000110001 6
b101001100110000 0
b10 !
b10 /
b0 "
b0 .
1-
15
b0 7
1'
#220000
b1 1
0'
0%
b10101 ,
#225000
14
b11110010110010101101100011011000110111101110111 2
b10100110101000000110000 6
b101001100110001 0
b1 "
b1 .
b10 1
0-
05
b1 7
1'
#230000
04
0'
1&
1%
0$
0#
b10110 ,
#235000
b110011101110010011001010110010101101110 3
b11100100110010101100100 2
b101001100110010 0
b0 !
b0 /
b10 "
b10 .
b10 7
1'
#240000
0'
b10111 ,
#245000
1'
#250000
b11 1
14
0'
0&
1$
1#
b11000 ,
#255000
04
b11110010110010101101100011011000110111101110111 3
b10100110101000000110001 6
b101001100110011 0
b1 !
b1 /
b0 1
1-
15
b11 7
1'
#260000
0'
b11001 ,
#265000
14
b11100100110010101100100 3
b110011101110010011001010110010101101110 2
b10100110101000000110000 6
b101001100110000 0
b10 !
b10 /
b0 "
b0 .
0-
05
b0 7
1'
#270000
b1 1
04
0'
0%
0$
0#
b11010 ,
#275000
b11110010110010101101100011011000110111101110111 2
b101001100110001 0
b1 "
b1 .
b10 1
b1 7
1'
#280000
0'
1&
1%
b11011 ,
#285000
b110011101110010011001010110010101101110 3
b11100100110010101100100 2
b101001100110010 0
b0 !
b0 /
b10 "
b10 .
b10 7
1'
#290000
b11 1
14
0'
0&
1$
1#
b11100 ,
#295000
04
b11110010110010101101100011011000110111101110111 3
b10100110101000000110001 6
b101001100110011 0
b1 !
b1 /
b0 1
1-
15
b11 7
1'
#300000
0'
0%
b11101 ,
#305000
14
b11100100110010101100100 3
b110011101110010011001010110010101101110 2
b10100110101000000110000 6
b101001100110000 0
b10 !
b10 /
b0 "
b0 .
b1 1
0-
05
b0 7
1'
#310000
0'
1&
b11110 ,
#315000
04
b11110010110010101101100011011000110111101110111 2
b10100110101000000110001 6
b101001100110001 0
b1 "
b1 .
b10 1
1-
15
b1 7
1'
#320000
0'
0&
1%
b11111 ,
#325000
14
b110011101110010011001010110010101101110 3
b11100100110010101100100 2
b10100110101000000110000 6
b101001100110010 0
b0 !
b0 /
b10 "
b10 .
b11 1
0-
05
b10 7
1'
#330000
04
0'
0$
0#
b100000 ,
#335000
b11110010110010101101100011011000110111101110111 3
b101001100110011 0
b1 !
b1 /
b0 1
b11 7
1'
#340000
0'
1&
b100001 ,
#345000
b11100100110010101100100 3
b110011101110010011001010110010101101110 2
b101001100110000 0
b10 !
b10 /
b0 "
b0 .
b0 7
1'
#350000
0'
0&
b100010 ,
#355000
1'
#360000
0'
b100011 ,
#365000
1'
#370000
b1 1
0'
1&
0%
1$
b100100 ,
#375000
b11110010110010101101100011011000110111101110111 2
b101001100110001 0
b1 "
b1 .
b10 1
b1 7
1'
#380000
14
0'
1%
1#
b100101 ,
#385000
04
b110011101110010011001010110010101101110 3
b11100100110010101100100 2
b10100110101000000110001 6
b101001100110010 0
b0 !
b0 /
b10 "
b10 .
1-
15
b10 7
1'
#390000
14
0'
0%
0$
0#
b100110 ,
#395000
1'
#400000
0'
1%
b100111 ,
#405000
1'
#410000
0'
0%
b101000 ,
#415000
1'
#420000
0'
0&
1#
b101001 ,
#425000
1'
#430000
04
0'
1$
b101010 ,
#435000
b10100110101000000110000 6
14
b11 1
0-
05
1'
#440000
04
0'
0#
b101011 ,
#445000
b11110010110010101101100011011000110111101110111 3
b101001100110011 0
b1 !
b1 /
b0 1
b11 7
1'
#450000
14
0'
0$
1#
b101100 ,
#455000
b11100100110010101100100 3
b110011101110010011001010110010101101110 2
b10100110101000000110001 6
b101001100110000 0
b10 !
b10 /
b0 "
b0 .
b1 1
1-
15
b0 7
1'
#460000
b0 1
0'
1&
1%
b101101 ,
#465000
1'
#470000
b1 1
0'
0&
0%
0#
b101110 ,
#475000
b11110010110010101101100011011000110111101110111 2
b101001100110001 0
b1 "
b1 .
b10 1
b1 7
1'
#480000
0'
1#
b101111 ,
#485000
b110011101110010011001010110010101101110 3
b11100100110010101100100 2
b101001100110010 0
b0 !
b0 /
b10 "
b10 .
b10 7
1'
#490000
04
0'
1&
1%
1$
0#
b110000 ,
#495000
b10100110101000000110000 6
0-
05
1'
#500000
0'
b110001 ,
#505000
1'
#510000
0'
b110010 ,
