projects/verilog_tutorials/project_0/05_fsm_traffic_light/fsm_traffic.v
// ==================================================
//	[ VLSISYS Lab. ]
//	* Author		: HyeRyun Lim (imh2880@gmail.com)
//	* Filename		: fsm_traffic.v
//	* Date			: 2024-06-28 16:32:43
//	* Description	: 
// ==================================================
module fsm_traffic_light
(
	input clk,
	input rstn,
	input Ta,
	input Tb,
	input M,
	output reg  [1:0] La,
	output reg	[1:0] Lb
);

	localparam S0 = 0;
	localparam S1 = 1;
	localparam S2 = 2;
	localparam S3 = 3;
	
	parameter green = 0, yellow = 1, red = 2;

	reg [1:0] state, next_state;

	always @ (*) begin
		case(state)
			S0 : next_state = Ta ? S0 : S1;
			S1 : next_state = S2;
			S2 : next_state = (~M & ~Tb) ? S3 : S2;
			S3 : next_state = S0;
		endcase
	end

	always @ (posedge clk) begin
		if(!rstn)
			state <= S0;
		else
			state <= next_state;
	end

	always @ (*) begin
		case(state)
			S0 : begin
				La = green;
				Lb = red;
			end
			S1 : begin
				La = yellow;
				Lb = red;
			end
			S2 : begin
				La = red;
				Lb = green;
			end
			S3 : begin
				La = red;
				Lb = yellow;
			end
		endcase
	end

	`ifdef	DEBUG
			reg [8*32-1:0] light_stateMonitor;
			reg [8*32-1:0] out_La_stateMonitor;
			reg [8*32-1:0] out_Lb_stateMonitor;
			always @ (*) begin
				case(state)
					S0 : light_stateMonitor = "S0";
					S1 : light_stateMonitor = "S1";
					S2 : light_stateMonitor = "S2";
					S3 : light_stateMonitor = "S3";
				endcase

				case(La)
					green : out_La_stateMonitor = "green";
					yellow : out_La_stateMonitor = "yellow";
					red : out_La_stateMonitor = "red";
				endcase

				case(Lb)
					green : out_Lb_stateMonitor = "green";
					yellow : out_Lb_stateMonitor = "yellow";
					red : out_Lb_stateMonitor = "red";
				endcase

			end
		`endif
endmodule

module fsm_parade
(
	input clk,
	input rstn,
	input P,
	input R,
	output M
);

	localparam S0 = 0;
	localparam S1 = 1;

	reg state, next_state;

	always @ (*) begin
		case(state)
			S0 : next_state = P ? S1 : S0;
			S1 : next_state = R ? S0 : S1;
		endcase
	end

	always @ (posedge clk) begin
		if(!rstn)
			state <= S0;
		else
			state <= next_state;
	end
	
	assign M = (state == S1);

	
	`ifdef	DEBUG
			reg [8*32-1:0] parade_stateMonitor;
			always @ (*) begin
				case(state)
					S0 : parade_stateMonitor = "S0";
					S1 : parade_stateMonitor = "S1";
				endcase
			end
		`endif

endmodule

projects/verilog_tutorials/project_0/05_fsm_traffic_light/fsm_traffic_tb.v
// --------------------------------------------------
//	Define Global Variables
// --------------------------------------------------
`define	CLKFREQ		100		// Clock Freq. (Unit: MHz)
`define	SIMCYCLE	`NVEC	// Sim. Cycles
`define NVEC		50		// # of Test Vector
`define DEBUG

// --------------------------------------------------
//	Includes
// --------------------------------------------------
`include	"fsm_traffic.v"

module fsm_traffic_tb;
// --------------------------------------------------
//	DUT Signals & Instantiate
// --------------------------------------------------
	reg clk;
	reg rstn;
	reg P;
	reg R;
	reg Ta;
	reg Tb;
	wire M;
	wire [1:0] La;
	wire [1:0] Lb;

	fsm_traffic_light
	u_fsm_traffic_light(
		.clk				(clk				),
		.rstn				(rstn				),
		.Ta					(Ta					),
		.Tb					(Tb					),
		.M					(M					),
		.La					(La					),
		.Lb					(Lb					)
	);

	fsm_parade
	u_fsm_parade(
		.clk				(clk				),
		.rstn				(rstn				),
		.P					(P					),
		.R					(R					),
		.M					(M					)
	);



// --------------------------------------------------
//	Tasks
// --------------------------------------------------
	reg [8*32-1:0] taskState;
	integer err = 0;

	task init;
		begin
			taskState = "Init";
			clk = 0;
			rstn = 0;
			P = 0;
			R = 0;
			Ta = 0;
			Tb = 0;
		end
	endtask

	task resetReleaseAfterNCycles;
		input [9:0] n;
		begin
			taskState = "Reset On";
			rstn = 1'b0;
			#(1000/`CLKFREQ);
			rstn = 1'b1; 
			taskState = "Reset OFF";
		end
	endtask

	always #(500/`CLKFREQ) clk = ~clk;

// --------------------------------------------------
//	Test Stimulus
// --------------------------------------------------
	integer		i, j;
	initial begin
		init();
		resetReleaseAfterNCycles(4);

		for (i=0; i<`SIMCYCLE; i++) begin
			P = $urandom;
			R = $urandom;
			Ta = $urandom;
			Tb = $urandom;
			#(1000/`CLKFREQ);
		end
		$finish;
	end

// --------------------------------------------------
//	Dump VCD
// --------------------------------------------------
	reg	[8*32-1:0]	vcd_file;
	initial begin
		if ($value$plusargs("vcd_file=%s", vcd_file)) begin
			$dumpfile(vcd_file);
			$dumpvars;
		end else begin
			$dumpfile("fsm_traffic_tb.vcd");
			$dumpvars;
		end
	end

endmodule

projects/verilog_tutorials/project_0/05_fsm_traffic_light/vcd/fsm_traffic.vcd
$date
	Fri Jun 28 17:34:27 2024
$end
$version
	Icarus Verilog
$end
$timescale
	1ps
$end
$scope module fsm_traffic_tb $end
$var wire 1 ! M $end
$var wire 2 " Lb [1:0] $end
$var wire 2 # La [1:0] $end
$var reg 1 $ P $end
$var reg 1 % R $end
$var reg 1 & Ta $end
$var reg 1 ' Tb $end
$var reg 1 ( clk $end
$var reg 1 ) rstn $end
$var reg 256 * taskState [255:0] $end
$var reg 256 + vcd_file [255:0] $end
$var integer 32 , err [31:0] $end
$var integer 32 - i [31:0] $end
$scope module u_fsm_parade $end
$var wire 1 $ P $end
$var wire 1 % R $end
$var wire 1 ( clk $end
$var wire 1 ) rstn $end
$var wire 1 ! M $end
$var reg 1 . next_state $end
$var reg 256 / parade_stateMonitor [255:0] $end
$var reg 1 0 state $end
$upscope $end
$scope module u_fsm_traffic_light $end
$var wire 1 ! M $end
$var wire 1 & Ta $end
$var wire 1 ' Tb $end
$var wire 1 ( clk $end
$var wire 1 ) rstn $end
$var reg 2 1 La [1:0] $end
$var reg 2 2 Lb [1:0] $end
$var reg 256 3 light_stateMonitor [255:0] $end
$var reg 2 4 next_state [1:0] $end
$var reg 256 5 out_La_stateMonitor [255:0] $end
$var reg 256 6 out_Lb_stateMonitor [255:0] $end
$var reg 2 7 state [1:0] $end
$upscope $end
$scope task init $end
$upscope $end
$scope task resetReleaseAfterNCycles $end
$var reg 10 8 n [9:0] $end
$upscope $end
$upscope $end
$enddefinitions $end
#0
$dumpvars
b100 8
bx 7
bx 6
bx 5
bx 4
bx 3
bx 2
bx 1
x0
bx /
x.
bx -
b0 ,
b1011100010111101110110011000110110010000101111011001100111001101101101010111110111010001110010011000010110011001100110011010010110001100101110011101100110001101100100 +
b101001001100101011100110110010101110100001000000100111101101110 *
0)
0(
0'
0&
0%
0$
bx #
bx "
x!
$end
#5000
b11100100110010101100100 6
b110011101110010011001010110010101101110 5
b101001100110000 3
b10 "
b10 2
b0 #
b0 1
b101001100110000 /
0.
b1 4
b0 7
0!
00
1(
#10000
b0 4
0(
1'
1&
1%
b0 -
b10100100110010101110011011001010111010000100000010011110100011001000110 *
1)
#15000
1(
#20000
1.
0(
0'
1$
b1 -
#25000
b101001100110001 /
0.
1!
10
1(
#30000
b1 4
0(
1'
0&
b10 -
#35000
b101001100110000 /
1.
b11110010110010101101100011011000110111101110111 5
b101001100110001 3
b1 #
b1 1
b10 4
0!
00
b1 7
1(
#40000
0(
0'
1&
0%
b11 -
#45000
b110011101110010011001010110010101101110 6
b11100100110010101100100 5
b101001100110010 3
b0 "
b0 2
b10 #
b10 1
b101001100110001 /
b10 7
1!
10
1(
#50000
0(
1'
b100 -
#55000
1(
#60000
0.
0(
0'
0&
1%
0$
b101 -
#65000
b101001100110000 /
b11 4
0!
00
1(
#70000
b10 4
0(
1'
b110 -
#75000
1(
#80000
b11 4
1.
0(
0'
1&
1$
b111 -
#85000
b11110010110010101101100011011000110111101110111 6
b101001100110011 3
b1 "
b1 2
b101001100110001 /
0.
b0 4
b11 7
1!
10
1(
#90000
1.
0(
1'
0&
0%
0$
b1000 -
#95000
b11100100110010101100100 6
b110011101110010011001010110010101101110 5
b101001100110000 3
b10 "
b10 2
b0 #
b0 1
b1 4
b0 7
1(
#100000
b0 4
0.
0(
1&
1%
b1001 -
#105000
b101001100110000 /
0!
00
1(
#110000
b1 4
1.
0(
0'
0&
1$
b1010 -
#115000
b101001100110001 /
0.
b11110010110010101101100011011000110111101110111 5
b101001100110001 3
b1 #
b1 1
b10 4
1!
10
b1 7
1(
#120000
0(
1&
b1011 -
#125000
b110011101110010011001010110010101101110 6
b11100100110010101100100 5
b101001100110010 3
b0 "
b0 2
b10 #
b10 1
b101001100110000 /
1.
b11 4
b10 7
0!
00
1(
#130000
0.
0(
0&
0%
0$
b1100 -
#135000
b11110010110010101101100011011000110111101110111 6
b101001100110011 3
b1 "
b1 2
b0 4
b11 7
1(
#140000
1.
0(
1'
1$
b1101 -
#145000
b11100100110010101100100 6
b110011101110010011001010110010101101110 5
b101001100110000 3
b10 "
b10 2
b0 #
b0 1
b101001100110001 /
b1 4
b0 7
1!
10
1(
#150000
0(
0'
b1110 -
#155000
b11110010110010101101100011011000110111101110111 5
b101001100110001 3
b1 #
b1 1
b10 4
b1 7
1(
#160000
0(
1'
1&
0$
b1111 -
#165000
b110011101110010011001010110010101101110 6
b11100100110010101100100 5
b101001100110010 3
b0 "
b0 2
b10 #
b10 1
b10 7
1(
#170000
0.
0(
0'
1%
1$
b10000 -
#175000
b101001100110000 /
1.
b11 4
0!
00
1(
#180000
b10 4
0.
0(
1'
0$
b10001 -
#185000
1(
#190000
0(
0%
b10010 -
#195000
1(
#200000
b11 4
0(
0'
1%
b10011 -
#205000
b11110010110010101101100011011000110111101110111 6
b101001100110011 3
b1 "
b1 2
b0 4
b11 7
1(
#210000
1.
0(
1$
b10100 -
#215000
b101001100110001 /
0.
b11100100110010101100100 6
b110011101110010011001010110010101101110 5
b101001100110000 3
b10 "
b10 2
b0 #
b0 1
1!
10
b0 7
1(
#220000
b1 4
0(
0&
b10101 -
#225000
b11110010110010101101100011011000110111101110111 5
b101001100110001 3
b1 #
b1 1
b101001100110000 /
1.
b10 4
b1 7
0!
00
1(
#230000
0.
0(
1'
1&
0%
0$
b10110 -
#235000
b110011101110010011001010110010101101110 6
b11100100110010101100100 5
b101001100110010 3
b0 "
b0 2
b10 #
b10 1
b10 7
1(
#240000
0(
b10111 -
#245000
1(
#250000
b11 4
1.
0(
0'
1%
1$
b11000 -
#255000
b101001100110001 /
0.
b11110010110010101101100011011000110111101110111 6
b101001100110011 3
b1 "
b1 2
b0 4
1!
10
b11 7
1(
#260000
0(
b11001 -
#265000
b11100100110010101100100 6
b110011101110010011001010110010101101110 5
b101001100110000 3
b10 "
b10 2
b0 #
b0 1
b101001100110000 /
1.
b0 7
0!
00
1(
#270000
b1 4
0.
0(
0&
0%
0$
b11010 -
#275000
b11110010110010101101100011011000110111101110111 5
b101001100110001 3
b1 #
b1 1
b10 4
b1 7
1(
#280000
0(
1'
1&
b11011 -
#285000
b110011101110010011001010110010101101110 6
b11100100110010101100100 5
b101001100110010 3
b0 "
b0 2
b10 #
b10 1
b10 7
1(
#290000
b11 4
1.
0(
0'
1%
1$
b11100 -
#295000
b101001100110001 /
0.
b11110010110010101101100011011000110111101110111 6
b101001100110011 3
b1 "
b1 2
b0 4
1!
10
b11 7
1(
#300000
0(
0&
b11101 -
#305000
b11100100110010101100100 6
b110011101110010011001010110010101101110 5
b101001100110000 3
b10 "
b10 2
b0 #
b0 1
b101001100110000 /
1.
b1 4
b0 7
0!
00
1(
#310000
0(
1'
b11110 -
#315000
b101001100110001 /
0.
b11110010110010101101100011011000110111101110111 5
b101001100110001 3
b1 #
b1 1
b10 4
1!
10
b1 7
1(
#320000
0(
0'
1&
b11111 -
#325000
b110011101110010011001010110010101101110 6
b11100100110010101100100 5
b101001100110010 3
b0 "
b0 2
b10 #
b10 1
b101001100110000 /
1.
b11 4
b10 7
0!
00
1(
#330000
0.
0(
0%
0$
b100000 -
#335000
b11110010110010101101100011011000110111101110111 6
b101001100110011 3
b1 "
b1 2
b0 4
b11 7
1(
#340000
0(
1'
b100001 -
#345000
b11100100110010101100100 6
b110011101110010011001010110010101101110 5
b101001100110000 3
b10 "
b10 2
b0 #
b0 1
b0 7
1(
#350000
0(
0'
b100010 -
#355000
1(
#360000
0(
b100011 -
#365000
1(
#370000
b1 4
0(
1'
0&
1%
b100100 -
#375000
b11110010110010101101100011011000110111101110111 5
b101001100110001 3
b1 #
b1 1
b10 4
b1 7
1(
#380000
1.
0(
1&
1$
b100101 -
#385000
b110011101110010011001010110010101101110 6
b11100100110010101100100 5
b101001100110010 3
b0 "
b0 2
b10 #
b10 1
b101001100110001 /
0.
b10 7
1!
10
1(
#390000
1.
0(
0&
0%
0$
b100110 -
#395000
1(
#400000
0(
1&
b100111 -
#405000
1(
#410000
0(
0&
b101000 -
#415000
1(
#420000
0(
0'
1$
b101001 -
#425000
1(
#430000
0.
0(
1%
b101010 -
#435000
b101001100110000 /
1.
b11 4
0!
00
1(
#440000
0.
0(
0$
b101011 -
#445000
b11110010110010101101100011011000110111101110111 6
b101001100110011 3
b1 "
b1 2
b0 4
b11 7
1(
#450000
1.
0(
0%
1$
b101100 -
#455000
b101001100110001 /
b11100100110010101100100 6
b110011101110010011001010110010101101110 5
b101001100110000 3
b10 "
b10 2
b0 #
b0 1
b1 4
1!
10
b0 7
1(
#460000
b0 4
0(
1'
1&
b101101 -
#465000
1(
#470000
b1 4
0(
0'
0&
0$
b101110 -
#475000
b11110010110010101101100011011000110111101110111 5
b101001100110001 3
b1 #
b1 1
b10 4
b1 7
1(
#480000
0(
1$
b101111 -
#485000
b110011101110010011001010110010101101110 6
b11100100110010101100100 5
b101001100110010 3
b0 "
b0 2
b10 #
b10 1
b10 7
1(
#490000
0.
0(
1'
1&
1%
0$
b110000 -
#495000
b101001100110000 /
0!
00
1(
#500000
0(
b110001 -
#505000
1(
#510000
0(
b110010 -
