projects/verilog_tutorials/project_0/06_sram_extension/sram_extension.v
// ==================================================
//	[ VLSISYS Lab. ]
//	* Author		: HyeRyun Lim (imh2880@gmail.com)
//	* Filename		: sram_extension.v
//	* Date			: 2024-07-01 10:27:18
//	* Description	: 
// ==================================================

module sram_extension
(
	input		  clk,
	input		  wen,
	input		  cen,
	input		  oen,
	input  [5:0]  addr,
	input  [63:0] i_data,
	output [63:0] o_data
);

	spsram
	#(
		.BW_DATA			(32					),
		.BW_ADDR			(4					)
	)
	u_spsram0(
		.clk				(clk				),
		.wen				(wen				),
		.cen				(~addr[5] & ~addr[4]),
		.oen				(~addr[5] & ~addr[4]),
		.addr				(addr[3:0]			),
		.i_data				(i_data[31:0]		),
		.o_data				(o_data[31:0]		)
	);

	spsram
	#(
		.BW_DATA			(32					),
		.BW_ADDR			(4					)
	)
	u_spsram1(
		.clk				(clk				),
		.wen				(wen				),
		.cen				(~addr[5] & ~addr[4]),
		.oen				(~addr[5] & ~addr[4]),
		.addr				(addr[3:0]			),
		.i_data				(i_data[63:32]		),
		.o_data				(o_data[63:32]		)
	);

	spsram
	#(
		.BW_DATA			(32					),
		.BW_ADDR			(4					)
	)
	u_spsram2(
		.clk				(clk				),
		.wen				(wen				),
		.cen				(~addr[5] & addr[4] ),
		.oen				(~addr[5] & addr[4] ),
		.addr				(addr[3:0]			),
		.i_data				(i_data[31:0]		),
		.o_data				(o_data[31:0]		)
	);

	spsram
	#(
		.BW_DATA			(32					),
		.BW_ADDR			(4					)
	)
	u_spsram3(
		.clk				(clk				),
		.wen				(wen				),
		.cen				(~addr[5] & addr[4] ),
		.oen				(~addr[5] & addr[4] ),
		.addr				(addr[3:0]			),
		.i_data				(i_data[63:32]		),
		.o_data				(o_data[63:32]		)
	);

	spsram
	#(
		.BW_DATA			(32					),
		.BW_ADDR			(4					)
	)
	u_spsram4(
		.clk				(clk				),
		.wen				(wen				),
		.cen				(addr[5] & ~addr[4] ),
		.oen				(addr[5] & ~addr[4] ),
		.addr				(addr[3:0]			),
		.i_data				(i_data[31:0]		),
		.o_data				(o_data[31:0]		)
	);

	spsram
	#(
		.BW_DATA			(32					),
		.BW_ADDR			(4					)
	)
	u_spsram5(
		.clk				(clk				),
		.wen				(wen				),
		.cen				(addr[5] & ~addr[4] ),
		.oen				(addr[5] & ~addr[4] ),
		.addr				(addr[3:0]			),
		.i_data				(i_data[63:32]		),
		.o_data				(o_data[63:32]		)
	);

	spsram
	#(
		.BW_DATA			(32					),
		.BW_ADDR			(4					)
	)
	u_spsram6(
		.clk				(clk				),
		.wen				(wen				),
		.cen				(addr[5] & addr[4]  ),
		.oen				(addr[5] & addr[4]  ),
		.addr				(addr[3:0]			),
		.i_data				(i_data[31:0]		),
		.o_data				(o_data[31:0]		)
	);

	spsram
	#(
		.BW_DATA			(32					),
		.BW_ADDR			(4					)
	)
	u_spsram7(
		.clk				(clk				),
		.wen				(wen				),
		.cen				(addr[5] & addr[4]  ),
		.oen				(addr[5] & addr[4]  ),
		.addr				(addr[3:0]			),
		.i_data				(i_data[63:32]		),
		.o_data				(o_data[63:32]		)
	);
endmodule

module spsram
#(
	parameter	BW_DATA = 32,
	parameter	BW_ADDR = 4
)
(
	input				 clk,
	input				 wen,
	input				 cen,
	input				 oen,
	input  [BW_ADDR-1:0] addr,
	input  [BW_DATA-1:0] i_data,
	output [BW_DATA-1:0] o_data
);

	// Memory Write
	reg		[BW_DATA-1:0]	mem[0:2**BW_ADDR-1];

	always @ (posedge clk) begin
		if(cen && wen)
			mem[addr] <= i_data;
		else
			mem[addr] <= mem[addr];
	end

	// Memory Read
	`ifdef	SPSRAM_ASYNC
		assign o_data = !oen ? 'bz :
						(cen && !wen) ? mem[addr] : 'bx;
	`else //sync
		reg		[BW_DATA-1:0] o_data;
		always @ (posedge clk) begin
			if(oen) begin
				if(cen && !wen)
					o_data <= mem[addr];
				else
					o_data <= 'bx;
			end
			else
				o_data <= 'bz;
		end
	`endif

endmodule

projects/verilog_tutorials/project_0/06_sram_extension/sram_extension_tb.v
// --------------------------------------------------
//	Define Global Variables
// --------------------------------------------------
`define	CLKFREQ		100		// Clock Freq. (Unit: MHz)
`define	SIMCYCLE	`NVEC	// Sim. Cycles
`define NVEC		64		// # of Test Vector

// --------------------------------------------------
//	Includes
// --------------------------------------------------
`include	"sram_extension.v"

module sram_extension_tb;
// --------------------------------------------------
//	DUT Signals & Instantiate
// --------------------------------------------------
	reg		 	clk;
	reg		 	wen;
	reg		    cen;
	reg		 	oen;
	reg  [5:0]  addr;
	reg  [63:0] i_data;
	wire [63:0] o_data;

	sram_extension
	u_sram_extension(
		.clk				(clk				),
		.wen				(wen				),
		.cen				(cen				),
		.oen				(oen				),
		.addr				(addr				),
		.i_data				(i_data				),
		.o_data				(o_data				)
	);

// --------------------------------------------------
//	Tasks
// --------------------------------------------------
	reg [8*32-1:0] taskState;

	task init;
		begin
			taskState = "Init";
			clk = 0;
			wen = 0;
			cen = 0;
			oen = 0;
			addr = 0;
			i_data = 0;
		end
	endtask

	task memWR;
		input	[5:0] t_addr;
		input	[63:0] t_data;
		begin
			@(negedge clk) begin
				taskState = "WR";
				i_data = t_data;
				addr = t_addr;
				cen	 = 1;
				wen  = 1;
				oen  = 0;
			end
		end
	endtask

	task memRD;
		input	[5:0] t_addr;
		begin
			@(negedge clk) begin
				taskState = "RD";
				addr = t_addr;
				cen = 1;
				wen = 0;
				oen = 1;
			end
		end
	endtask

	always #(500/`CLKFREQ) clk = ~clk;

// --------------------------------------------------
//	Test Stimulus
// --------------------------------------------------
	integer		i, j;
	initial begin
		init();
		#(4*1000/`CLKFREQ);

		for (i=0; i<`SIMCYCLE; i++) begin
			memWR(i, i);
		end
		for (i=0; i<`SIMCYCLE; i++) begin
			memRD(i);
		end
		$finish;
	end

// --------------------------------------------------
//	Dump VCD
// --------------------------------------------------
	reg	[8*32-1:0]	vcd_file;
	initial begin
		if ($value$plusargs("vcd_file=%s", vcd_file)) begin
			$dumpfile(vcd_file);
			$dumpvars;
		end else begin
			$dumpfile("sram_extension_tb.vcd");
			$dumpvars;
		end
	end

endmodule

projects/verilog_tutorials/project_0/06_sram_extension/vcd/sram_extension.vcd
$date
	Mon Jul  8 17:25:33 2024
$end
$version
	Icarus Verilog
$end
$timescale
	1ps
$end
$scope module sram_extension_tb $end
$var wire 64 ! o_data [63:0] $end
$var reg 6 " addr [5:0] $end
$var reg 1 # cen $end
$var reg 1 $ clk $end
$var reg 64 % i_data [63:0] $end
$var reg 1 & oen $end
$var reg 256 ' taskState [255:0] $end
$var reg 256 ( vcd_file [255:0] $end
$var reg 1 ) wen $end
$var integer 32 * i [31:0] $end
$scope module u_sram_extension $end
$var wire 6 + addr [5:0] $end
$var wire 1 # cen $end
$var wire 1 $ clk $end
$var wire 64 , i_data [63:0] $end
$var wire 64 - o_data [63:0] $end
$var wire 1 & oen $end
$var wire 1 ) wen $end
$scope module u_spsram0 $end
$var wire 4 . addr [3:0] $end
$var wire 1 / cen $end
$var wire 1 $ clk $end
$var wire 32 0 i_data [31:0] $end
$var wire 1 1 oen $end
$var wire 1 ) wen $end
$var wire 32 2 o_data [31:0] $end
$upscope $end
$scope module u_spsram1 $end
$var wire 4 3 addr [3:0] $end
$var wire 1 4 cen $end
$var wire 1 $ clk $end
$var wire 32 5 i_data [31:0] $end
$var wire 1 6 oen $end
$var wire 1 ) wen $end
$var wire 32 7 o_data [31:0] $end
$upscope $end
$scope module u_spsram2 $end
$var wire 4 8 addr [3:0] $end
$var wire 1 9 cen $end
$var wire 1 $ clk $end
$var wire 32 : i_data [31:0] $end
$var wire 1 ; oen $end
$var wire 1 ) wen $end
$var wire 32 < o_data [31:0] $end
$upscope $end
$scope module u_spsram3 $end
$var wire 4 = addr [3:0] $end
$var wire 1 > cen $end
$var wire 1 $ clk $end
$var wire 32 ? i_data [31:0] $end
$var wire 1 @ oen $end
$var wire 1 ) wen $end
$var wire 32 A o_data [31:0] $end
$upscope $end
$scope module u_spsram4 $end
$var wire 4 B addr [3:0] $end
$var wire 1 C cen $end
$var wire 1 $ clk $end
$var wire 32 D i_data [31:0] $end
$var wire 1 E oen $end
$var wire 1 ) wen $end
$var wire 32 F o_data [31:0] $end
$upscope $end
$scope module u_spsram5 $end
$var wire 4 G addr [3:0] $end
$var wire 1 H cen $end
$var wire 1 $ clk $end
$var wire 32 I i_data [31:0] $end
$var wire 1 J oen $end
$var wire 1 ) wen $end
$var wire 32 K o_data [31:0] $end
$upscope $end
$scope module u_spsram6 $end
$var wire 4 L addr [3:0] $end
$var wire 1 M cen $end
$var wire 1 $ clk $end
$var wire 32 N i_data [31:0] $end
$var wire 1 O oen $end
$var wire 1 ) wen $end
$var wire 32 P o_data [31:0] $end
$upscope $end
$scope module u_spsram7 $end
$var wire 4 Q addr [3:0] $end
$var wire 1 R cen $end
$var wire 1 $ clk $end
$var wire 32 S i_data [31:0] $end
$var wire 1 T oen $end
$var wire 1 ) wen $end
$var wire 32 U o_data [31:0] $end
$upscope $end
$upscope $end
$scope task init $end
$upscope $end
$scope task memRD $end
$var reg 6 V t_addr [5:0] $end
$upscope $end
$scope task memWR $end
$var reg 6 W t_addr [5:0] $end
$var reg 64 X t_data [63:0] $end
$upscope $end
$upscope $end
$enddefinitions $end
#0
$dumpvars
bx X
bx W
bx V
bz U
0T
b0 S
0R
b0 Q
bz P
0O
b0 N
0M
b0 L
bz K
0J
b0 I
0H
b0 G
bz F
0E
b0 D
0C
b0 B
bz A
0@
b0 ?
0>
b0 =
bz <
0;
b0 :
09
b0 8
bx 7
16
b0 5
14
b0 3
bx 2
11
b0 0
1/
b0 .
bx -
b0 ,
b0 +
bx *
0)
b1011100010111101110110011000110110010000101111011100110111001001100001011011010101111101100101011110000111010001100101011011100111001101101001011011110110111000101110011101100110001101100100 (
b1001001011011100110100101110100 '
0&
b0 %
0$
0#
b0 "
bx !
$end
#5000
1$
#10000
0$
#15000
1$
#20000
1)
1#
b101011101010010 '
0$
b1 X
b1 W
b1 *
#25000
1$
#30000
b1 .
b1 3
b1 8
b1 =
b1 B
b1 G
b1 L
b1 Q
b1 0
b1 :
b1 D
b1 N
b10 X
b10 W
b10 *
b1 "
b1 +
b1 %
b1 ,
0$
#35000
1$
#40000
b10 .
b10 3
b10 8
b10 =
b10 B
b10 G
b10 L
b10 Q
b10 0
b10 :
b10 D
b10 N
b11 X
b11 W
b11 *
b10 "
b10 +
b10 %
b10 ,
0$
#45000
1$
#50000
b11 .
b11 3
b11 8
b11 =
b11 B
b11 G
b11 L
b11 Q
b11 0
b11 :
b11 D
b11 N
b100 X
b100 W
b100 *
b11 "
b11 +
b11 %
b11 ,
0$
#55000
1$
#60000
b100 .
b100 3
b100 8
b100 =
b100 B
b100 G
b100 L
b100 Q
b100 0
b100 :
b100 D
b100 N
b101 X
b101 W
b101 *
b100 "
b100 +
b100 %
b100 ,
0$
#65000
1$
#70000
b101 .
b101 3
b101 8
b101 =
b101 B
b101 G
b101 L
b101 Q
b101 0
b101 :
b101 D
b101 N
b110 X
b110 W
b110 *
b101 "
b101 +
b101 %
b101 ,
0$
#75000
1$
#80000
b110 .
b110 3
b110 8
b110 =
b110 B
b110 G
b110 L
b110 Q
b110 0
b110 :
b110 D
b110 N
b111 X
b111 W
b111 *
b110 "
b110 +
b110 %
b110 ,
0$
#85000
1$
#90000
b111 .
b111 3
b111 8
b111 =
b111 B
b111 G
b111 L
b111 Q
b111 0
b111 :
b111 D
b111 N
b1000 X
b1000 W
b1000 *
b111 "
b111 +
b111 %
b111 ,
0$
#95000
1$
#100000
b1000 .
b1000 3
b1000 8
b1000 =
b1000 B
b1000 G
b1000 L
b1000 Q
b1000 0
b1000 :
b1000 D
b1000 N
b1001 X
b1001 W
b1001 *
b1000 "
b1000 +
b1000 %
b1000 ,
0$
#105000
1$
#110000
b1001 .
b1001 3
b1001 8
b1001 =
b1001 B
b1001 G
b1001 L
b1001 Q
b1001 0
b1001 :
b1001 D
b1001 N
b1010 X
b1010 W
b1010 *
b1001 "
b1001 +
b1001 %
b1001 ,
0$
#115000
1$
#120000
b1010 .
b1010 3
b1010 8
b1010 =
b1010 B
b1010 G
b1010 L
b1010 Q
b1010 0
b1010 :
b1010 D
b1010 N
b1011 X
b1011 W
b1011 *
b1010 "
b1010 +
b1010 %
b1010 ,
0$
#125000
1$
#130000
b1011 .
b1011 3
b1011 8
b1011 =
b1011 B
b1011 G
b1011 L
b1011 Q
b1011 0
b1011 :
b1011 D
b1011 N
b1100 X
b1100 W
b1100 *
b1011 "
b1011 +
b1011 %
b1011 ,
0$
#135000
1$
#140000
b1100 .
b1100 3
b1100 8
b1100 =
b1100 B
b1100 G
b1100 L
b1100 Q
b1100 0
b1100 :
b1100 D
b1100 N
b1101 X
b1101 W
b1101 *
b1100 "
b1100 +
b1100 %
b1100 ,
0$
#145000
1$
#150000
b1101 .
b1101 3
b1101 8
b1101 =
b1101 B
b1101 G
b1101 L
b1101 Q
b1101 0
b1101 :
b1101 D
b1101 N
b1110 X
b1110 W
b1110 *
b1101 "
b1101 +
b1101 %
b1101 ,
0$
#155000
1$
#160000
b1110 .
b1110 3
b1110 8
b1110 =
b1110 B
b1110 G
b1110 L
b1110 Q
b1110 0
b1110 :
b1110 D
b1110 N
b1111 X
b1111 W
b1111 *
b1110 "
b1110 +
b1110 %
b1110 ,
0$
#165000
1$
#170000
b1111 .
b1111 3
b1111 8
b1111 =
b1111 B
b1111 G
b1111 L
b1111 Q
b1111 0
b1111 :
b1111 D
b1111 N
b10000 X
b10000 W
b10000 *
b1111 "
b1111 +
b1111 %
b1111 ,
0$
#175000
1$
#180000
bz 2
bz 7
0/
01
04
06
bx <
bx A
19
1;
1>
1@
b0 .
b0 3
b0 8
b0 =
b0 B
b0 G
b0 L
b0 Q
b10000 0
b10000 :
b10000 D
b10000 N
b10001 X
b10001 W
b10001 *
b10000 "
b10000 +
b10000 %
b10000 ,
0$
#185000
1$
#190000
b1 .
b1 3
b1 8
b1 =
b1 B
b1 G
b1 L
b1 Q
b10001 0
b10001 :
b10001 D
b10001 N
b10010 X
b10010 W
b10010 *
b10001 "
b10001 +
b10001 %
b10001 ,
0$
#195000
1$
#200000
b10 .
b10 3
b10 8
b10 =
b10 B
b10 G
b10 L
b10 Q
b10010 0
b10010 :
b10010 D
b10010 N
b10011 X
b10011 W
b10011 *
b10010 "
b10010 +
b10010 %
b10010 ,
0$
#205000
1$
#210000
b11 .
b11 3
b11 8
b11 =
b11 B
b11 G
b11 L
b11 Q
b10011 0
b10011 :
b10011 D
b10011 N
b10100 X
b10100 W
b10100 *
b10011 "
b10011 +
b10011 %
b10011 ,
0$
#215000
1$
#220000
b100 .
b100 3
b100 8
b100 =
b100 B
b100 G
b100 L
b100 Q
b10100 0
b10100 :
b10100 D
b10100 N
b10101 X
b10101 W
b10101 *
b10100 "
b10100 +
b10100 %
b10100 ,
0$
#225000
1$
#230000
b101 .
b101 3
b101 8
b101 =
b101 B
b101 G
b101 L
b101 Q
b10101 0
b10101 :
b10101 D
b10101 N
b10110 X
b10110 W
b10110 *
b10101 "
b10101 +
b10101 %
b10101 ,
0$
#235000
1$
#240000
b110 .
b110 3
b110 8
b110 =
b110 B
b110 G
b110 L
b110 Q
b10110 0
b10110 :
b10110 D
b10110 N
b10111 X
b10111 W
b10111 *
b10110 "
b10110 +
b10110 %
b10110 ,
0$
#245000
1$
#250000
b111 .
b111 3
b111 8
b111 =
b111 B
b111 G
b111 L
b111 Q
b10111 0
b10111 :
b10111 D
b10111 N
b11000 X
b11000 W
b11000 *
b10111 "
b10111 +
b10111 %
b10111 ,
0$
#255000
1$
#260000
b1000 .
b1000 3
b1000 8
b1000 =
b1000 B
b1000 G
b1000 L
b1000 Q
b11000 0
b11000 :
b11000 D
b11000 N
b11001 X
b11001 W
b11001 *
b11000 "
b11000 +
b11000 %
b11000 ,
0$
#265000
1$
#270000
b1001 .
b1001 3
b1001 8
b1001 =
b1001 B
b1001 G
b1001 L
b1001 Q
b11001 0
b11001 :
b11001 D
b11001 N
b11010 X
b11010 W
b11010 *
b11001 "
b11001 +
b11001 %
b11001 ,
0$
#275000
1$
#280000
b1010 .
b1010 3
b1010 8
b1010 =
b1010 B
b1010 G
b1010 L
b1010 Q
b11010 0
b11010 :
b11010 D
b11010 N
b11011 X
b11011 W
b11011 *
b11010 "
b11010 +
b11010 %
b11010 ,
0$
#285000
1$
#290000
b1011 .
b1011 3
b1011 8
b1011 =
b1011 B
b1011 G
b1011 L
b1011 Q
b11011 0
b11011 :
b11011 D
b11011 N
b11100 X
b11100 W
b11100 *
b11011 "
b11011 +
b11011 %
b11011 ,
0$
#295000
1$
#300000
b1100 .
b1100 3
b1100 8
b1100 =
b1100 B
b1100 G
b1100 L
b1100 Q
b11100 0
b11100 :
b11100 D
b11100 N
b11101 X
b11101 W
b11101 *
b11100 "
b11100 +
b11100 %
b11100 ,
0$
#305000
1$
#310000
b1101 .
b1101 3
b1101 8
b1101 =
b1101 B
b1101 G
b1101 L
b1101 Q
b11101 0
b11101 :
b11101 D
b11101 N
b11110 X
b11110 W
b11110 *
b11101 "
b11101 +
b11101 %
b11101 ,
0$
#315000
1$
#320000
b1110 .
b1110 3
b1110 8
b1110 =
b1110 B
b1110 G
b1110 L
b1110 Q
b11110 0
b11110 :
b11110 D
b11110 N
b11111 X
b11111 W
b11111 *
b11110 "
b11110 +
b11110 %
b11110 ,
0$
#325000
1$
#330000
b1111 .
b1111 3
b1111 8
b1111 =
b1111 B
b1111 G
b1111 L
b1111 Q
b11111 0
b11111 :
b11111 D
b11111 N
b100000 X
b100000 W
b100000 *
b11111 "
b11111 +
b11111 %
b11111 ,
0$
#335000
1$
#340000
bz <
bz A
bx F
bx K
09
0;
0>
0@
1C
1E
1H
1J
b0 .
b0 3
b0 8
b0 =
b0 B
b0 G
b0 L
b0 Q
b100000 0
b100000 :
b100000 D
b100000 N
b100001 X
b100001 W
b100001 *
b100000 "
b100000 +
b100000 %
b100000 ,
0$
#345000
1$
#350000
b1 .
b1 3
b1 8
b1 =
b1 B
b1 G
b1 L
b1 Q
b100001 0
b100001 :
b100001 D
b100001 N
b100010 X
b100010 W
b100010 *
b100001 "
b100001 +
b100001 %
b100001 ,
0$
#355000
1$
#360000
b10 .
b10 3
b10 8
b10 =
b10 B
b10 G
b10 L
b10 Q
b100010 0
b100010 :
b100010 D
b100010 N
b100011 X
b100011 W
b100011 *
b100010 "
b100010 +
b100010 %
b100010 ,
0$
#365000
1$
#370000
b11 .
b11 3
b11 8
b11 =
b11 B
b11 G
b11 L
b11 Q
b100011 0
b100011 :
b100011 D
b100011 N
b100100 X
b100100 W
b100100 *
b100011 "
b100011 +
b100011 %
b100011 ,
0$
#375000
1$
#380000
b100 .
b100 3
b100 8
b100 =
b100 B
b100 G
b100 L
b100 Q
b100100 0
b100100 :
b100100 D
b100100 N
b100101 X
b100101 W
b100101 *
b100100 "
b100100 +
b100100 %
b100100 ,
0$
#385000
1$
#390000
b101 .
b101 3
b101 8
b101 =
b101 B
b101 G
b101 L
b101 Q
b100101 0
b100101 :
b100101 D
b100101 N
b100110 X
b100110 W
b100110 *
b100101 "
b100101 +
b100101 %
b100101 ,
0$
#395000
1$
#400000
b110 .
b110 3
b110 8
b110 =
b110 B
b110 G
b110 L
b110 Q
b100110 0
b100110 :
b100110 D
b100110 N
b100111 X
b100111 W
b100111 *
b100110 "
b100110 +
b100110 %
b100110 ,
0$
#405000
1$
#410000
b111 .
b111 3
b111 8
b111 =
b111 B
b111 G
b111 L
b111 Q
b100111 0
b100111 :
b100111 D
b100111 N
b101000 X
b101000 W
b101000 *
b100111 "
b100111 +
b100111 %
b100111 ,
0$
#415000
1$
#420000
b1000 .
b1000 3
b1000 8
b1000 =
b1000 B
b1000 G
b1000 L
b1000 Q
b101000 0
b101000 :
b101000 D
b101000 N
b101001 X
b101001 W
b101001 *
b101000 "
b101000 +
b101000 %
b101000 ,
0$
#425000
1$
#430000
b1001 .
b1001 3
b1001 8
b1001 =
b1001 B
b1001 G
b1001 L
b1001 Q
b101001 0
b101001 :
b101001 D
b101001 N
b101010 X
b101010 W
b101010 *
b101001 "
b101001 +
b101001 %
b101001 ,
0$
#435000
1$
#440000
b1010 .
b1010 3
b1010 8
b1010 =
b1010 B
b1010 G
b1010 L
b1010 Q
b101010 0
b101010 :
b101010 D
b101010 N
b101011 X
b101011 W
b101011 *
b101010 "
b101010 +
b101010 %
b101010 ,
0$
#445000
1$
#450000
b1011 .
b1011 3
b1011 8
b1011 =
b1011 B
b1011 G
b1011 L
b1011 Q
b101011 0
b101011 :
b101011 D
b101011 N
b101100 X
b101100 W
b101100 *
b101011 "
b101011 +
b101011 %
b101011 ,
0$
#455000
1$
#460000
b1100 .
b1100 3
b1100 8
b1100 =
b1100 B
b1100 G
b1100 L
b1100 Q
b101100 0
b101100 :
b101100 D
b101100 N
b101101 X
b101101 W
b101101 *
b101100 "
b101100 +
b101100 %
b101100 ,
0$
#465000
1$
#470000
b1101 .
b1101 3
b1101 8
b1101 =
b1101 B
b1101 G
b1101 L
b1101 Q
b101101 0
b101101 :
b101101 D
b101101 N
b101110 X
b101110 W
b101110 *
b101101 "
b101101 +
b101101 %
b101101 ,
0$
#475000
1$
#480000
b1110 .
b1110 3
b1110 8
b1110 =
b1110 B
b1110 G
b1110 L
b1110 Q
b101110 0
b101110 :
b101110 D
b101110 N
b101111 X
b101111 W
b101111 *
b101110 "
b101110 +
b101110 %
b101110 ,
0$
#485000
1$
#490000
b1111 .
b1111 3
b1111 8
b1111 =
b1111 B
b1111 G
b1111 L
b1111 Q
b101111 0
b101111 :
b101111 D
b101111 N
b110000 X
b110000 W
b110000 *
b101111 "
b101111 +
b101111 %
b101111 ,
0$
#495000
1$
#500000
bz F
bz K
0C
0E
0H
0J
bx P
bx U
1M
1O
1R
1T
b0 .
b0 3
b0 8
b0 =
b0 B
b0 G
b0 L
b0 Q
b110000 0
b110000 :
b110000 D
b110000 N
b110001 X
b110001 W
b110001 *
b110000 "
b110000 +
b110000 %
b110000 ,
0$
#505000
1$
#510000
b1 .
b1 3
b1 8
b1 =
b1 B
b1 G
b1 L
b1 Q
b110001 0
b110001 :
b110001 D
b110001 N
b110010 X
b110010 W
b110010 *
b110001 "
b110001 +
b110001 %
b110001 ,
0$
#515000
1$
#520000
b10 .
b10 3
b10 8
b10 =
b10 B
b10 G
b10 L
b10 Q
b110010 0
b110010 :
b110010 D
b110010 N
b110011 X
b110011 W
b110011 *
b110010 "
b110010 +
b110010 %
b110010 ,
0$
#525000
1$
#530000
b11 .
b11 3
b11 8
b11 =
b11 B
b11 G
b11 L
b11 Q
b110011 0
b110011 :
b110011 D
b110011 N
b110100 X
b110100 W
b110100 *
b110011 "
b110011 +
b110011 %
b110011 ,
0$
#535000
1$
#540000
b100 .
b100 3
b100 8
b100 =
b100 B
b100 G
b100 L
b100 Q
b110100 0
b110100 :
b110100 D
b110100 N
b110101 X
b110101 W
b110101 *
b110100 "
b110100 +
b110100 %
b110100 ,
0$
#545000
1$
#550000
b101 .
b101 3
b101 8
b101 =
b101 B
b101 G
b101 L
b101 Q
b110101 0
b110101 :
b110101 D
b110101 N
b110110 X
b110110 W
b110110 *
b110101 "
b110101 +
b110101 %
b110101 ,
0$
#555000
1$
#560000
b110 .
b110 3
b110 8
b110 =
b110 B
b110 G
b110 L
b110 Q
b110110 0
b110110 :
b110110 D
b110110 N
b110111 X
b110111 W
b110111 *
b110110 "
b110110 +
b110110 %
b110110 ,
0$
#565000
1$
#570000
b111 .
b111 3
b111 8
b111 =
b111 B
b111 G
b111 L
b111 Q
b110111 0
b110111 :
b110111 D
b110111 N
b111000 X
b111000 W
b111000 *
b110111 "
b110111 +
b110111 %
b110111 ,
0$
#575000
1$
#580000
b1000 .
b1000 3
b1000 8
b1000 =
b1000 B
b1000 G
b1000 L
b1000 Q
b111000 0
b111000 :
b111000 D
b111000 N
b111001 X
b111001 W
b111001 *
b111000 "
b111000 +
b111000 %
b111000 ,
0$
#585000
1$
#590000
b1001 .
b1001 3
b1001 8
b1001 =
b1001 B
b1001 G
b1001 L
b1001 Q
b111001 0
b111001 :
b111001 D
b111001 N
b111010 X
b111010 W
b111010 *
b111001 "
b111001 +
b111001 %
b111001 ,
0$
#595000
1$
#600000
b1010 .
b1010 3
b1010 8
b1010 =
b1010 B
b1010 G
b1010 L
b1010 Q
b111010 0
b111010 :
b111010 D
b111010 N
b111011 X
b111011 W
b111011 *
b111010 "
b111010 +
b111010 %
b111010 ,
0$
#605000
1$
#610000
b1011 .
b1011 3
b1011 8
b1011 =
b1011 B
b1011 G
b1011 L
b1011 Q
b111011 0
b111011 :
b111011 D
b111011 N
b111100 X
b111100 W
b111100 *
b111011 "
b111011 +
b111011 %
b111011 ,
0$
#615000
1$
#620000
b1100 .
b1100 3
b1100 8
b1100 =
b1100 B
b1100 G
b1100 L
b1100 Q
b111100 0
b111100 :
b111100 D
b111100 N
b111101 X
b111101 W
b111101 *
b111100 "
b111100 +
b111100 %
b111100 ,
0$
#625000
1$
#630000
b1101 .
b1101 3
b1101 8
b1101 =
b1101 B
b1101 G
b1101 L
b1101 Q
b111101 0
b111101 :
b111101 D
b111101 N
b111110 X
b111110 W
b111110 *
b111101 "
b111101 +
b111101 %
b111101 ,
0$
#635000
1$
#640000
b1110 .
b1110 3
b1110 8
b1110 =
b1110 B
b1110 G
b1110 L
b1110 Q
b111110 0
b111110 :
b111110 D
b111110 N
b111111 X
b111111 W
b111111 *
b111110 "
b111110 +
b111110 %
b111110 ,
0$
#645000
1$
#650000
b1111 .
b1111 3
b1111 8
b1111 =
b1111 B
b1111 G
b1111 L
b1111 Q
b111111 0
b111111 :
b111111 D
b111111 N
b0 V
b0 *
b111111 "
b111111 +
b111111 %
b111111 ,
0$
#655000
1$
#660000
b0 2
b0 7
1/
11
14
16
bz P
b0 !
b0 -
bz U
0M
0O
0R
0T
b0 .
b0 3
b0 8
b0 =
b0 B
b0 G
b0 L
b0 Q
b1 V
b1 *
1&
0)
b0 "
b0 +
b101001001000100 '
0$
#665000
1$
#670000
b1 !
b1 -
b1 2
b1 .
b1 3
b1 8
b1 =
b1 B
b1 G
b1 L
b1 Q
b10 V
b10 *
b1 "
b1 +
0$
#675000
1$
#680000
b10 !
b10 -
b10 2
b10 .
b10 3
b10 8
b10 =
b10 B
b10 G
b10 L
b10 Q
b11 V
b11 *
b10 "
b10 +
0$
#685000
1$
#690000
b11 !
b11 -
b11 2
b11 .
b11 3
b11 8
b11 =
b11 B
b11 G
b11 L
b11 Q
b100 V
b100 *
b11 "
b11 +
0$
#695000
1$
#700000
b100 !
b100 -
b100 2
b100 .
b100 3
b100 8
b100 =
b100 B
b100 G
b100 L
b100 Q
b101 V
b101 *
b100 "
b100 +
0$
#705000
1$
#710000
b101 !
b101 -
b101 2
b101 .
b101 3
b101 8
b101 =
b101 B
b101 G
b101 L
b101 Q
b110 V
b110 *
b101 "
b101 +
0$
#715000
1$
#720000
b110 !
b110 -
b110 2
b110 .
b110 3
b110 8
b110 =
b110 B
b110 G
b110 L
b110 Q
b111 V
b111 *
b110 "
b110 +
0$
#725000
1$
#730000
b111 !
b111 -
b111 2
b111 .
b111 3
b111 8
b111 =
b111 B
b111 G
b111 L
b111 Q
b1000 V
b1000 *
b111 "
b111 +
0$
#735000
1$
#740000
b1000 !
b1000 -
b1000 2
b1000 .
b1000 3
b1000 8
b1000 =
b1000 B
b1000 G
b1000 L
b1000 Q
b1001 V
b1001 *
b1000 "
b1000 +
0$
#745000
1$
#750000
b1001 !
b1001 -
b1001 2
b1001 .
b1001 3
b1001 8
b1001 =
b1001 B
b1001 G
b1001 L
b1001 Q
b1010 V
b1010 *
b1001 "
b1001 +
0$
#755000
1$
#760000
b1010 !
b1010 -
b1010 2
b1010 .
b1010 3
b1010 8
b1010 =
b1010 B
b1010 G
b1010 L
b1010 Q
b1011 V
b1011 *
b1010 "
b1010 +
0$
#765000
1$
#770000
b1011 !
b1011 -
b1011 2
b1011 .
b1011 3
b1011 8
b1011 =
b1011 B
b1011 G
b1011 L
b1011 Q
b1100 V
b1100 *
b1011 "
b1011 +
0$
#775000
1$
#780000
b1100 !
b1100 -
b1100 2
b1100 .
b1100 3
b1100 8
b1100 =
b1100 B
b1100 G
b1100 L
b1100 Q
b1101 V
b1101 *
b1100 "
b1100 +
0$
#785000
1$
#790000
b1101 !
b1101 -
b1101 2
b1101 .
b1101 3
b1101 8
b1101 =
b1101 B
b1101 G
b1101 L
b1101 Q
b1110 V
b1110 *
b1101 "
b1101 +
0$
#795000
1$
#800000
b1110 !
b1110 -
b1110 2
b1110 .
b1110 3
b1110 8
b1110 =
b1110 B
b1110 G
b1110 L
b1110 Q
b1111 V
b1111 *
b1110 "
b1110 +
0$
#805000
1$
#810000
b1111 !
b1111 -
b1111 2
b1111 .
b1111 3
b1111 8
b1111 =
b1111 B
b1111 G
b1111 L
b1111 Q
b10000 V
b10000 *
b1111 "
b1111 +
0$
#815000
1$
#820000
bz 7
0/
01
bz 2
04
06
b10000 <
b10000 !
b10000 -
b0 A
19
1;
1>
1@
b0 .
b0 3
b0 8
b0 =
b0 B
b0 G
b0 L
b0 Q
b10001 V
b10001 *
b10000 "
b10000 +
0$
#825000
1$
#830000
b10001 !
b10001 -
b10001 <
b1 .
b1 3
b1 8
b1 =
b1 B
b1 G
b1 L
b1 Q
b10010 V
b10010 *
b10001 "
b10001 +
0$
#835000
1$
#840000
b10010 !
b10010 -
b10010 <
b10 .
b10 3
b10 8
b10 =
b10 B
b10 G
b10 L
b10 Q
b10011 V
b10011 *
b10010 "
b10010 +
0$
#845000
1$
