projects/combinational/01_mux/mux2.v
module mux2_assign
(
	input    i_sel,
	input    i_in0,
	input    i_in1,
	output   o_out
);

	assign o_out = i_sel ? i_in1 : i_in0;

endmodule

module mux2_if
(
	input          i_sel,
	input          i_in0,
	input          i_in1,
	output   reg   o_out
);

	always @ (*) begin
		if(i_sel == 0)
			o_out = i_in0;
		else
			o_out = i_in1;
	end

endmodule

module mux2_case
(
	input          i_sel,
	input          i_in0,
	input          i_in1,
	output   reg   o_out
);

	always @ (*) begin
		case(i_sel)
			0 : o_out = i_in0;
			1 : o_out = i_in1;
		endcase
	end

endmodule

projects/zaram_training_course/02_combinational_logic/01_mux/mux2_tb.v
`include "mux2.v"

module mux2_tb;

// ========================================
// Module Instanciation
// ========================================
	reg    i_sel;
	reg    i_in0;
	reg    i_in1;
	wire   o_out_assign;
	wire   o_out_if;
	wire   o_out_case;

	mux2_assign u_0
	(
		.i_sel         (i_sel),
		.i_in0         (i_in0),
		.i_in1         (i_in1),
		.o_out   (o_out_assign)
	);

	mux2_if u_1
	(
		.i_sel (i_sel),
		.i_in0 (i_in0),
		.i_in1 (i_in1),
		.o_out (o_out_if)
	);

	mux2_case u_2
	(
		.i_sel (i_sel),
		.i_in0 (i_in0),
		.i_in1 (i_in1),
		.o_out (o_out_case)
	);

	integer i;
	initial begin
		for(i=0; i<10; i++) begin
			{i_sel, i_in0, i_in1} = $urandom_range(0, 7);
			#(100);
		end	
		$finish;
	end

	reg [8*32-1:0]  vcd_file;
    initial begin
        if ($value$plusargs("vcd_file=%s", vcd_file)) begin
            $dumpfile(vcd_file);
            $dumpvars;
        end
    end
 
endmodule

projects/zaram_training_course/02_combinational_logic/01_mux/vcd/mux2.vcd
$date
	Tue Jun 25 13:36:32 2024
$end
$version
	Icarus Verilog
$end
$timescale
	1ps
$end
$scope module mux2_tb $end
$var wire 1 ! o_out_if $end
$var wire 1 " o_out_case $end
$var wire 1 # o_out_assign $end
$var reg 1 $ i_in0 $end
$var reg 1 % i_in1 $end
$var reg 1 & i_sel $end
$var reg 256 ' vcd_file [255:0] $end
$var integer 32 ( i [31:0] $end
$scope module u_0 $end
$var wire 1 $ i_in0 $end
$var wire 1 % i_in1 $end
$var wire 1 & i_sel $end
$var wire 1 # o_out $end
$upscope $end
$scope module u_1 $end
$var wire 1 $ i_in0 $end
$var wire 1 % i_in1 $end
$var wire 1 & i_sel $end
$var reg 1 ! o_out $end
$upscope $end
$scope module u_2 $end
$var wire 1 $ i_in0 $end
$var wire 1 % i_in1 $end
$var wire 1 & i_sel $end
$var reg 1 " o_out $end
$upscope $end
$upscope $end
$enddefinitions $end
#0
$dumpvars
b0 (
b10111000101111011101100110001101100100001011110110110101110101011110000011001000101110011101100110001101100100 '
1&
0%
0$
0#
0"
0!
$end
#100000
1#
1!
1"
0&
1$
b1 (
#200000
0#
0"
0!
0$
b10 (
#300000
1%
b11 (
#400000
1&
0%
b100 (
#500000
1$
b101 (
#600000
0&
0$
1%
b110 (
#700000
0%
b111 (
#800000
1&
b1000 (
#900000
b1001 (
#1000000
b1010 (
