projects/zaram_training_course/02_combinational_logic/02_dec/dec2.v
module dec2_dataflow
(
	input    [1:0]   i_in,
	input            i_en,
	output   [3:0]   o_out
);
	
	assign o_out = i_en ? (4'd1 << i_in) : 4'd0;
endmodule

module dec2_behavior
(
	input    [1:0]   i_in,
	input    i_en,
	output   reg     [3:0]   o_out
);
	
	always @ (*) begin
		if(i_en == 1) begin
			case(i_in)
				0 : o_out = 4'b0001;
				1 : o_out = 4'b0010;
				2 : o_out = 4'b0100;
				3 : o_out = 4'b1000;
			endcase
		end
		else
			o_out = 4'd0;
	end
endmodule

projects/zaram_training_course/02_combinational_logic/02_dec/dec2_tb.v
`define CLKFREQ		10 //MHz
`define SIMCYCLE	20

`include "dec2.v"

module dec2_tb ();

	reg    [1:0]   i_in;
	reg 		   i_en;
	wire   [3:0]   o_out_dataflow;
	wire   [3:0]   o_out_behavior;

	dec2_dataflow
	u_dec2_dataflow
	(
		.i_in(i_in),
		.i_en(i_en),
		.o_out(o_out_dataflow)
	);

	dec2_behavior
	u_dec2_behavior
	(
		.i_in(i_in),
		.i_en(i_en),
		.o_out(o_out_behavior)
	);

	task init;
		begin
			i_in = 0;
			i_en = 0;
		end
	endtask

	integer i;
	initial begin
		init();
		for(i=0; i<`SIMCYCLE; i++) begin
			{i_in, i_en} = $urandom_range(0, 7);
			#(1000/`CLKFREQ);
		end
		$finish;
	end

	reg	[8*32-1:0]	vcd_file;
	initial begin
		if ($value$plusargs("vcd_file=%s", vcd_file)) begin
			$dumpfile(vcd_file);
			$dumpvars;
		end 
		else begin
			$dumpfile("dec2_tb.vcd");
			$dumpvars;
		end
	end
endmodule

projects/zaram_training_course/02_combinational_logic/02_dec/vcd/dec2.vcd
$date
	Thu Jun 20 16:55:47 2024
$end
$version
	Icarus Verilog
$end
$timescale
	1ps
$end
$scope module dec2_tb $end
$var wire 4 ! o_out_dataflow [3:0] $end
$var wire 4 " o_out_behavior [3:0] $end
$var reg 1 # i_en $end
$var reg 2 $ i_in [1:0] $end
$var reg 256 % vcd_file [255:0] $end
$var integer 32 & i [31:0] $end
$scope module u_dec2_behavior $end
$var wire 1 # i_en $end
$var wire 2 ' i_in [1:0] $end
$var reg 4 ( o_out [3:0] $end
$upscope $end
$scope module u_dec2_dataflow $end
$var wire 1 # i_en $end
$var wire 2 ) i_in [1:0] $end
$var wire 4 * o_out [3:0] $end
$upscope $end
$scope task init $end
$upscope $end
$upscope $end
$enddefinitions $end
#0
$dumpvars
b0 *
b10 )
b0 (
b10 '
b0 &
b10111000101111011101100110001101100100001011110110010001100101011000110011001000101110011101100110001101100100 %
b10 $
0#
b0 "
b0 !
$end
#100000
b1 $
b1 '
b1 )
b1 &
#200000
b0 $
b0 '
b0 )
b10 &
#300000
b1 "
b1 (
b1 !
b1 *
1#
b11 &
#400000
b0 "
b0 (
b0 !
b0 *
b10 $
b10 '
b10 )
0#
b100 &
#500000
b11 $
b11 '
b11 )
b101 &
#600000
b1 "
b1 (
b1 !
b1 *
b0 $
b0 '
b0 )
1#
b110 &
#700000
b0 "
b0 (
b0 !
b0 *
0#
b111 &
#800000
b10 $
b10 '
b10 )
b1000 &
#900000
b1001 &
#1000000
b100 "
b100 (
b100 !
b100 *
1#
b1010 &
#1100000
b0 "
b0 (
b0 !
b0 *
0#
b1011 &
#1200000
b1000 "
b1000 (
b1000 !
b1000 *
b11 $
b11 '
b11 )
1#
b1100 &
#1300000
b0 "
b0 (
b0 !
b0 *
0#
b1101 &
#1400000
b1000 "
b1000 (
b1000 !
b1000 *
1#
b1110 &
#1500000
b10 "
b10 (
b10 !
b10 *
b1 $
b1 '
b1 )
b1111 &
#1600000
b10000 &
#1700000
b0 "
b0 (
b0 !
b0 *
0#
b10001 &
#1800000
b1000 "
b1000 (
b1000 !
b1000 *
b11 $
b11 '
b11 )
1#
b10010 &
#1900000
b1 "
b1 (
b1 !
b1 *
b0 $
b0 '
b0 )
b10011 &
#2000000
b10100 &
