projects/zaram_training_course/01_test/test/mux2.v
module  mux2
(
    output      o_out,
    input       i_sel,
    input       i_in0,
    input       i_in1
);

    assign  o_out   = i_sel ? i_in1 : i_in0;

endmodule

projects/zaram_training_course/01_test/test/mux2_tb.v
`timescale 1ns/1ps
`define CLKFREQ     100     // Unit: MHz
`define SIMCYCLE    100

`include    "mux2.v"

module  mux2_tb;
// ------------------------------------------
//  DUT Signals & Instantiate
// ------------------------------------------
    wire        o_out;
    reg         i_sel;
    reg         i_in0;
    reg         i_in1;

    mux2
    u_mux2
    (   
        .o_out      (o_out      ),
        .i_sel      (i_sel      ),
        .i_in0      (i_in0      ),
        .i_in1      (i_in1      )
    );

// --------------------------------------------------
//  Test Stimulus
// --------------------------------------------------
    integer     i;
    initial begin
        for (i=0; i<`SIMCYCLE; i++) begin
            {i_sel, i_in0, i_in1} = $urandom_range(0,7);
            #(1000/`CLKFREQ);
        end
		$finish;
    end

    reg [8*32-1:0]  vcd_file;
    initial begin
        if ($value$plusargs("vcd_file=%s", vcd_file)) begin
            $dumpfile(vcd_file);
            $dumpvars;
        end
    end

endmodule

projects/zaram_training_course/01_test/test/mux2.vcd
$date
	Tue Jun 11 10:11:49 2024
$end
$version
	Icarus Verilog
$end
$timescale
	1ps
$end
$scope module mux2_tb $end
$var wire 1 ! o_out $end
$var reg 1 " i_in0 $end
$var reg 1 # i_in1 $end
$var reg 1 $ i_sel $end
$var reg 256 % vcd_file [255:0] $end
$var integer 32 & i [31:0] $end
$scope module u_mux2 $end
$var wire 1 " i_in0 $end
$var wire 1 # i_in1 $end
$var wire 1 $ i_sel $end
$var wire 1 ! o_out $end
$upscope $end
$upscope $end
$enddefinitions $end
#0
$dumpvars
b0 &
b110110101110101011110000011001000101110011101100110001101100100 %
1$
0#
0"
0!
$end
#10000
1!
0$
1"
b1 &
#20000
0!
0"
b10 &
#30000
1#
b11 &
#40000
1$
0#
b100 &
#50000
1"
b101 &
#60000
0$
0"
1#
b110 &
#70000
0#
b111 &
#80000
1$
b1000 &
#90000
b1001 &
#100000
1!
1#
b1010 &
#110000
0!
0#
b1011 &
#120000
1!
1"
1#
b1100 &
#130000
0!
0#
b1101 &
#140000
1!
1#
b1110 &
#150000
0$
b1111 &
#160000
b10000 &
#170000
0#
b10001 &
#180000
1$
1#
b10010 &
#190000
0!
0$
0"
b10011 &
#200000
0#
b10100 &
#210000
1$
1"
b10101 &
#220000
1!
1#
b10110 &
#230000
0$
b10111 &
#240000
b11000 &
#250000
b11001 &
#260000
1$
0"
b11010 &
#270000
0$
1"
0#
b11011 &
#280000
0!
0"
b11100 &
#290000
1#
b11101 &
#300000
b11110 &
#310000
1$
0#
b11111 &
#320000
1!
0$
1"
b100000 &
#330000
0!
1$
0"
b100001 &
#340000
1"
b100010 &
#350000
1!
0$
b100011 &
#360000
b100100 &
#370000
0!
0"
b100101 &
#380000
b100110 &
#390000
1#
b100111 &
#400000
1!
1$
b101000 &
#410000
0$
1"
b101001 &
#420000
0!
0"
0#
b101010 &
#430000
1!
1"
b101011 &
#440000
0!
1$
0"
b101100 &
#450000
1!
0$
1"
1#
b101101 &
#460000
0!
1$
0"
0#
b101110 &
#470000
b101111 &
#480000
1!
0$
1"
1#
b110000 &
#490000
0!
0"
0#
b110001 &
#500000
1!
1$
1"
1#
b110010 &
#510000
0!
0#
b110011 &
#520000
1!
0"
1#
b110100 &
#530000
0$
1"
b110101 &
#540000
1$
0"
b110110 &
#550000
0$
1"
0#
b110111 &
#560000
1$
1#
b111000 &
#570000
0!
0#
b111001 &
#580000
1!
1#
b111010 &
#590000
0!
0#
b111011 &
#600000
1!
0$
b111100 &
#610000
0!
1$
0"
b111101 &
#620000
0$
b111110 &
#630000
1#
b111111 &
#640000
1$
1"
0#
b1000000 &
#650000
1!
0"
1#
b1000001 &
#660000
0!
0$
0#
b1000010 &
#670000
1$
b1000011 &
#680000
0$
1#
b1000100 &
#690000
1$
0#
b1000101 &
#700000
1!
1"
1#
b1000110 &
#710000
b1000111 &
#720000
0"
b1001000 &
#730000
b1001001 &
#740000
0!
1"
0#
b1001010 &
#750000
b1001011 &
#760000
1!
1#
b1001100 &
#770000
0$
0#
b1001101 &
#780000
b1001110 &
#790000
0!
0"
1#
b1001111 &
#800000
b1010000 &
#810000
1$
1"
0#
b1010001 &
#820000
0$
0"
1#
b1010010 &
#830000
1!
1"
b1010011 &
#840000
b1010100 &
#850000
0!
0"
b1010101 &
#860000
1$
1"
0#
b1010110 &
#870000
0"
b1010111 &
#880000
1!
0$
1"
1#
b1011000 &
#890000
1$
b1011001 &
#900000
0!
0$
0"
b1011010 &
#910000
1$
0#
b1011011 &
#920000
b1011100 &
#930000
0$
1#
b1011101 &
#940000
1!
1$
b1011110 &
#950000
0!
0#
b1011111 &
#960000
b1100000 &
#970000
1!
0$
1"
1#
b1100001 &
#980000
0!
1$
0#
b1100010 &
#990000
0$
0"
1#
b1100011 &
#1000000
b1100100 &
