projects/zaram_training_course/02_combinational_logic/03_adder/signed_adder.v
module signed_adder
(
	input signed [3:0] a,
	input 		 [3:0] b,
	input			   cin,
	output signed [4:0] sum
);

	assign sum = {a[3],a} - {1'b0, b};

endmodule

projects/zaram_training_course/02_combinational_logic/03_adder/signed_adder_tb.v
// --------------------------------------------------
//	Define Global Variables
// --------------------------------------------------
`define	CLKFREQ		100		// Clock Freq. (Unit: MHz)
`define	SIMCYCLE	`NVEC	// Sim. Cycles
`define NVEC		50		// # of Test Vector

// --------------------------------------------------
//	Includes
// --------------------------------------------------
`include	"signed_adder.v"

module signed_adder_tb;
// --------------------------------------------------
//	DUT Signals & Instantiate
// --------------------------------------------------
	reg signed [3:0] a;
	reg 		 [3:0] b;
	reg			   cin;
	wire signed [4:0] sum;

	signed_adder
	u_signed_adder(
		.a					(a					),
		.b					(b					),
		.cin				(cin				),
		.sum				(sum				)
	);

// --------------------------------------------------
//	Tasks
// --------------------------------------------------
	task init;
		begin
			a = 0;
			b = 0;
			cin = 0;
		end
	endtask

// --------------------------------------------------
//	Test Stimulus
// --------------------------------------------------
	integer		i, j;
	initial begin
		init();

		for (i=0; i<`SIMCYCLE; i++) begin
			a = $random;
			b = $random;
			cin = $random;
			#(1000/`CLKFREQ);
		end
		$finish;
	end

// --------------------------------------------------
//	Dump VCD
// --------------------------------------------------
	reg	[8*32-1:0]	vcd_file;
	initial begin
		if ($value$plusargs("vcd_file=%s", vcd_file)) begin
			$dumpfile(vcd_file);
			$dumpvars;
		end else begin
			$dumpfile("signed_adder_tb.vcd");
			$dumpvars;
		end
	end

endmodule

projects/zaram_training_course/02_combinational_logic/03_adder/vcd/signed_adder.vcd
$date
	Wed Jul  3 17:57:59 2024
$end
$version
	Icarus Verilog
$end
$timescale
	1ps
$end
$scope module signed_adder_tb $end
$var wire 5 ! sum [4:0] $end
$var reg 4 " a [3:0] $end
$var reg 4 # b [3:0] $end
$var reg 1 $ cin $end
$var reg 256 % vcd_file [255:0] $end
$var integer 32 & i [31:0] $end
$scope module u_signed_adder $end
$var wire 4 ' a [3:0] $end
$var wire 4 ( b [3:0] $end
$var wire 1 $ cin $end
$var wire 5 ) sum [4:0] $end
$upscope $end
$scope task init $end
$upscope $end
$upscope $end
$enddefinitions $end
#0
$dumpvars
b11 )
b1 (
b100 '
b0 &
b101110001011110111011001100011011001000010111101110011011010010110011101101110011001010110010001011111011000010110010001100100011001010111001000101110011101100110001101100100 %
1$
b1 #
b100 "
b11 !
$end
#10000
b1101 #
b1101 (
b10110 !
b10110 )
b11 "
b11 '
b1 &
#20000
b10 #
b10 (
b11 !
b11 )
b101 "
b101 '
b10 &
#30000
b110 #
b110 (
b10111 !
b10111 )
b1101 "
b1101 '
b11 &
#40000
b10001 !
b10001 )
b1100 #
b1100 (
b100 &
#50000
0$
b101 #
b101 (
b1 !
b1 )
b110 "
b110 '
b101 &
#60000
b111 #
b111 (
b11110 !
b11110 )
b101 "
b101 '
b110 &
#70000
b10 #
b10 (
b11101 !
b11101 )
b1111 "
b1111 '
b111 &
#80000
b101 #
b101 (
b10011 !
b10011 )
b1000 "
b1000 '
b1000 &
#90000
1$
b1101 #
b1101 (
b10000 !
b10000 )
b1101 "
b1101 '
b1001 &
#100000
0$
b1010 #
b1010 (
b11001 !
b11001 )
b11 "
b11 '
b1010 &
#110000
1$
b10110 !
b10110 )
b0 "
b0 '
b1011 &
#120000
b11 #
b11 (
b11 !
b11 )
b110 "
b110 '
b1100 &
#130000
b1011 #
b1011 (
b11000 !
b11000 )
b11 "
b11 '
b1101 &
#140000
b1110 #
b1110 (
b10100 !
b10100 )
b10 "
b10 '
b1110 &
#150000
0$
b11 #
b11 (
b11100 !
b11100 )
b1111 "
b1111 '
b1111 &
#160000
b1100 #
b1100 (
b1110 !
b1110 )
b1010 "
b1010 '
b10000 &
#170000
b11001 !
b11001 )
b1 #
b1 (
b10001 &
#180000
1$
b1001 #
b1001 (
b1111 !
b1111 )
b1000 "
b1000 '
b10010 &
#190000
0$
b110 #
b110 (
b0 !
b0 )
b110 "
b110 '
b10011 &
#200000
1$
b1010 #
b1010 (
b10010 !
b10010 )
b1100 "
b1100 '
b10100 &
#210000
b101 #
b101 (
b11100 !
b11100 )
b1 "
b1 '
b10101 &
#220000
0$
b1010 #
b1010 (
b10001 !
b10001 )
b1011 "
b1011 '
b10110 &
#230000
1$
b1 #
b1 (
b100 !
b100 )
b101 "
b101 '
b10111 &
#240000
b1100 #
b1100 (
b10110 !
b10110 )
b10 "
b10 '
b11000 &
#250000
b1000 #
b1000 (
b10111 !
b10111 )
b1111 "
b1111 '
b11001 &
#260000
b10011 !
b10011 )
b1100 #
b1100 (
b11010 &
#270000
0$
b1001 #
b1001 (
b10000 !
b10000 )
b1001 "
b1001 '
b11011 &
#280000
b1 #
b1 (
b110 !
b110 )
b111 "
b111 '
b11100 &
#290000
b10 #
b10 (
b11010 !
b11010 )
b1100 "
b1100 '
b11101 &
#300000
b1101 #
b1101 (
b11010 !
b11010 )
b111 "
b111 '
b11110 &
#310000
1$
b10001 !
b10001 )
b1110 "
b1110 '
b11111 &
#320000
b11 #
b11 (
b11100 !
b11100 )
b1111 "
b1111 '
b100000 &
#330000
b1011 #
b1011 (
b1101 !
b1101 )
b1000 "
b1000 '
b100001 &
#340000
0$
b1010 #
b1010 (
b10101 !
b10101 )
b1111 "
b1111 '
b100010 &
#350000
b1110 #
b1110 (
b11000 !
b11000 )
b110 "
b110 '
b100011 &
#360000
1$
b110 #
b110 (
b10100 !
b10100 )
b1010 "
b1010 '
b100100 &
#370000
b1111 #
b1111 (
b10100 !
b10100 )
b11 "
b11 '
b100101 &
#380000
b100 #
b100 (
b11011 !
b11011 )
b1111 "
b1111 '
b100110 &
#390000
0$
b110 #
b110 (
b10101 !
b10101 )
b1011 "
b1011 '
b100111 &
#400000
b1101 #
b1101 (
b1100 !
b1100 )
b1001 "
b1001 '
b101000 &
#410000
1$
b101 #
b101 (
b0 !
b0 )
b101 "
b101 '
b101001 &
#420000
0$
b100 #
b100 (
b10101 !
b10101 )
b1001 "
b1001 '
b101010 &
#430000
b1011 #
b1011 (
b1111 !
b1111 )
b1010 "
b1010 '
b101011 &
#440000
1$
b1010 #
b1010 (
b10010 !
b10010 )
b1100 "
b1100 '
b101100 &
#450000
0$
b110 #
b110 (
b11101 !
b11101 )
b11 "
b11 '
b101101 &
#460000
b1010 #
b1010 (
b11101 !
b11101 )
b111 "
b111 '
b101110 &
#470000
b1001 #
b1001 (
b1111 !
b1111 )
b1000 "
b1000 '
b101111 &
#480000
b11 #
b11 (
b1 !
b1 )
b100 "
b100 '
b110000 &
#490000
1$
b1011 #
b1011 (
b1110 !
b1110 )
b1001 "
b1001 '
b110001 &
#500000
b110010 &
